[
  {
    "theme": "Base Culture",
    "casts": 117,
    "posts": 50,
    "comments": 67,
    "likes": 321,
    "avg_score": "2.75",
    "top_author": "@statuette",
    "top_cast_url": "https://farcaster.xyz/statuette/0x76fe9cab"
  },
  {
    "theme": "Token/Promo",
    "casts": 41,
    "posts": 24,
    "comments": 17,
    "likes": 148,
    "avg_score": "3.76",
    "top_author": "@littleanjel",
    "top_cast_url": "https://farcaster.xyz/littleanjel/0x545eff78"
  },
  {
    "theme": "Apps/Games",
    "casts": 22,
    "posts": 2,
    "comments": 20,
    "likes": 46,
    "avg_score": "3.27",
    "top_author": "@sub",
    "top_cast_url": "https://farcaster.xyz/sub/0x0df6a2e8"
  },
  {
    "theme": "Security/Ops",
    "casts": 17,
    "posts": 6,
    "comments": 11,
    "likes": 38,
    "avg_score": "2.98",
    "top_author": "@vgr",
    "top_cast_url": "https://farcaster.xyz/vgr/0x58244e8e"
  },
  {
    "theme": "Protocol/Fork",
    "casts": 3,
    "posts": 3,
    "comments": 0,
    "likes": 3,
    "avg_score": "2.59",
    "top_author": "@snakeheadman042.base.eth",
    "top_cast_url": "https://farcaster.xyz/snakeheadman042.base.eth/0x54fec8d6"
  }
]
