[
  {
    "author": "@farcaster",
    "author_url": "https://farcaster.xyz/farcaster",
    "casts": 3,
    "posts": 2,
    "comments": 1,
    "likes": 101,
    "recasts": 14,
    "replies": 13,
    "best_score": "10.00",
    "top_cast_url": "https://farcaster.xyz/farcaster/0x2f739987",
    "avg_score": "6.49"
  },
  {
    "author": "@wake",
    "author_url": "https://farcaster.xyz/wake",
    "casts": 3,
    "posts": 1,
    "comments": 2,
    "likes": 50,
    "recasts": 1,
    "replies": 5,
    "best_score": "8.46",
    "top_cast_url": "https://farcaster.xyz/wake/0x8407aab1",
    "avg_score": "7.07"
  },
  {
    "author": "@ds8",
    "author_url": "https://farcaster.xyz/ds8",
    "casts": 3,
    "posts": 0,
    "comments": 3,
    "likes": 32,
    "recasts": 2,
    "replies": 0,
    "best_score": "7.49",
    "top_cast_url": "https://farcaster.xyz/ds8/0x8023d28d",
    "avg_score": "6.51"
  },
  {
    "author": "@road",
    "author_url": "https://farcaster.xyz/road",
    "casts": 3,
    "posts": 0,
    "comments": 3,
    "likes": 29,
    "recasts": 2,
    "replies": 17,
    "best_score": "7.74",
    "top_cast_url": "https://farcaster.xyz/road/0xcc6716ef",
    "avg_score": "5.98"
  },
  {
    "author": "@markcarey",
    "author_url": "https://farcaster.xyz/markcarey",
    "casts": 3,
    "posts": 1,
    "comments": 2,
    "likes": 19,
    "recasts": 0,
    "replies": 4,
    "best_score": "7.20",
    "top_cast_url": "https://farcaster.xyz/markcarey/0xa9013518",
    "avg_score": "4.82"
  },
  {
    "author": "@sahban",
    "author_url": "https://farcaster.xyz/sahban",
    "casts": 1,
    "posts": 1,
    "comments": 0,
    "likes": 18,
    "recasts": 0,
    "replies": 7,
    "best_score": "7.74",
    "top_cast_url": "https://farcaster.xyz/sahban/0xd5b034aa",
    "avg_score": "7.74"
  },
  {
    "author": "@hendrazk",
    "author_url": "https://farcaster.xyz/hendrazk",
    "casts": 1,
    "posts": 1,
    "comments": 0,
    "likes": 17,
    "recasts": 1,
    "replies": 1,
    "best_score": "7.62",
    "top_cast_url": "https://farcaster.xyz/hendrazk/0xb006ad62",
    "avg_score": "7.62"
  },
  {
    "author": "@sub",
    "author_url": "https://farcaster.xyz/sub",
    "casts": 3,
    "posts": 0,
    "comments": 3,
    "likes": 17,
    "recasts": 0,
    "replies": 6,
    "best_score": "6.03",
    "top_cast_url": "https://farcaster.xyz/sub/0x62dc7d84",
    "avg_score": "5.10"
  },
  {
    "author": "@icetoad",
    "author_url": "https://farcaster.xyz/icetoad",
    "casts": 2,
    "posts": 0,
    "comments": 2,
    "likes": 16,
    "recasts": 1,
    "replies": 6,
    "best_score": "7.04",
    "top_cast_url": "https://farcaster.xyz/icetoad/0xbb269d8e",
    "avg_score": "5.61"
  },
  {
    "author": "@muhammadind",
    "author_url": "https://farcaster.xyz/muhammadind",
    "casts": 2,
    "posts": 0,
    "comments": 2,
    "likes": 15,
    "recasts": 0,
    "replies": 3,
    "best_score": "6.87",
    "top_cast_url": "https://farcaster.xyz/muhammadind/0x191538b7",
    "avg_score": "5.52"
  },
  {
    "author": "@denizakar",
    "author_url": "https://farcaster.xyz/denizakar",
    "casts": 1,
    "posts": 1,
    "comments": 0,
    "likes": 14,
    "recasts": 0,
    "replies": 5,
    "best_score": "7.20",
    "top_cast_url": "https://farcaster.xyz/denizakar/0x87d129f1",
    "avg_score": "7.20"
  },
  {
    "author": "@alitiknazoglu",
    "author_url": "https://farcaster.xyz/alitiknazoglu",
    "casts": 2,
    "posts": 1,
    "comments": 1,
    "likes": 13,
    "recasts": 3,
    "replies": 4,
    "best_score": "6.87",
    "top_cast_url": "https://farcaster.xyz/alitiknazoglu/0xdf9a412e",
    "avg_score": "4.73"
  },
  {
    "author": "@zosphotos",
    "author_url": "https://farcaster.xyz/zosphotos",
    "casts": 1,
    "posts": 0,
    "comments": 1,
    "likes": 12,
    "recasts": 1,
    "replies": 4,
    "best_score": "6.87",
    "top_cast_url": "https://farcaster.xyz/zosphotos/0x4f643bca",
    "avg_score": "6.87"
  },
  {
    "author": "@jubjub",
    "author_url": "https://farcaster.xyz/jubjub",
    "casts": 2,
    "posts": 1,
    "comments": 1,
    "likes": 12,
    "recasts": 0,
    "replies": 2,
    "best_score": "6.69",
    "top_cast_url": "https://farcaster.xyz/jubjub/0x7886b459",
    "avg_score": "4.64"
  },
  {
    "author": "@depressivehacks",
    "author_url": "https://farcaster.xyz/depressivehacks",
    "casts": 2,
    "posts": 0,
    "comments": 2,
    "likes": 12,
    "recasts": 0,
    "replies": 5,
    "best_score": "5.45",
    "top_cast_url": "https://farcaster.xyz/depressivehacks/0x7e835c6f",
    "avg_score": "5.45"
  },
  {
    "author": "@statuette",
    "author_url": "https://farcaster.xyz/statuette",
    "casts": 1,
    "posts": 0,
    "comments": 1,
    "likes": 11,
    "recasts": 0,
    "replies": 4,
    "best_score": "6.69",
    "top_cast_url": "https://farcaster.xyz/statuette/0x54856489",
    "avg_score": "6.69"
  },
  {
    "author": "@dandelion",
    "author_url": "https://farcaster.xyz/dandelion",
    "casts": 1,
    "posts": 0,
    "comments": 1,
    "likes": 10,
    "recasts": 0,
    "replies": 1,
    "best_score": "6.49",
    "top_cast_url": "https://farcaster.xyz/dandelion/0x37ebe241",
    "avg_score": "6.49"
  },
  {
    "author": "@alpenflow",
    "author_url": "https://farcaster.xyz/alpenflow",
    "casts": 2,
    "posts": 2,
    "comments": 0,
    "likes": 10,
    "recasts": 1,
    "replies": 4,
    "best_score": "6.03",
    "top_cast_url": "https://farcaster.xyz/alpenflow/0x95438cf4",
    "avg_score": "4.77"
  },
  {
    "author": "@farabish",
    "author_url": "https://farcaster.xyz/farabish",
    "casts": 1,
    "posts": 0,
    "comments": 1,
    "likes": 9,
    "recasts": 1,
    "replies": 4,
    "best_score": "6.27",
    "top_cast_url": "https://farcaster.xyz/farabish/0xba1889fd",
    "avg_score": "6.27"
  },
  {
    "author": "@fuckcoolpussy",
    "author_url": "https://farcaster.xyz/fuckcoolpussy",
    "casts": 1,
    "posts": 0,
    "comments": 1,
    "likes": 9,
    "recasts": 0,
    "replies": 2,
    "best_score": "6.27",
    "top_cast_url": "https://farcaster.xyz/fuckcoolpussy/0xe09b0b59",
    "avg_score": "6.27"
  },
  {
    "author": "@ins0mn1a",
    "author_url": "https://farcaster.xyz/ins0mn1a",
    "casts": 1,
    "posts": 0,
    "comments": 1,
    "likes": 8,
    "recasts": 1,
    "replies": 1,
    "best_score": "6.03",
    "top_cast_url": "https://farcaster.xyz/ins0mn1a/0x8c3c9dd0",
    "avg_score": "6.03"
  },
  {
    "author": "@ethdaily",
    "author_url": "https://farcaster.xyz/ethdaily",
    "casts": 1,
    "posts": 0,
    "comments": 1,
    "likes": 7,
    "recasts": 0,
    "replies": 3,
    "best_score": "5.76",
    "top_cast_url": "https://farcaster.xyz/ethdaily/0x6b53c57a",
    "avg_score": "5.76"
  },
  {
    "author": "@hamdan",
    "author_url": "https://farcaster.xyz/hamdan",
    "casts": 1,
    "posts": 0,
    "comments": 1,
    "likes": 7,
    "recasts": 0,
    "replies": 2,
    "best_score": "5.76",
    "top_cast_url": "https://farcaster.xyz/hamdan/0x9611f5ff",
    "avg_score": "5.76"
  },
  {
    "author": "@kazishahporan",
    "author_url": "https://farcaster.xyz/kazishahporan",
    "casts": 1,
    "posts": 0,
    "comments": 1,
    "likes": 7,
    "recasts": 0,
    "replies": 0,
    "best_score": "5.76",
    "top_cast_url": "https://farcaster.xyz/kazishahporan/0xcb8bd026",
    "avg_score": "5.76"
  },
  {
    "author": "@fateme7360",
    "author_url": "https://farcaster.xyz/fateme7360",
    "casts": 1,
    "posts": 0,
    "comments": 1,
    "likes": 6,
    "recasts": 0,
    "replies": 3,
    "best_score": "5.45",
    "top_cast_url": "https://farcaster.xyz/fateme7360/0xd0476e84",
    "avg_score": "5.45"
  },
  {
    "author": "@darrylyeo",
    "author_url": "https://farcaster.xyz/darrylyeo",
    "casts": 1,
    "posts": 0,
    "comments": 1,
    "likes": 6,
    "recasts": 0,
    "replies": 2,
    "best_score": "5.45",
    "top_cast_url": "https://farcaster.xyz/darrylyeo/0x9ae026e0",
    "avg_score": "5.45"
  },
  {
    "author": "@mika2",
    "author_url": "https://farcaster.xyz/mika2",
    "casts": 1,
    "posts": 0,
    "comments": 1,
    "likes": 6,
    "recasts": 0,
    "replies": 0,
    "best_score": "5.45",
    "top_cast_url": "https://farcaster.xyz/mika2/0x457d1f8f",
    "avg_score": "5.45"
  },
  {
    "author": "@drmat",
    "author_url": "https://farcaster.xyz/drmat",
    "casts": 2,
    "posts": 0,
    "comments": 2,
    "likes": 6,
    "recasts": 1,
    "replies": 2,
    "best_score": "5.10",
    "top_cast_url": "https://farcaster.xyz/drmat/0xb3ed3c80",
    "avg_score": "3.84"
  },
  {
    "author": "@benido",
    "author_url": "https://farcaster.xyz/benido",
    "casts": 2,
    "posts": 0,
    "comments": 2,
    "likes": 6,
    "recasts": 0,
    "replies": 0,
    "best_score": "4.68",
    "top_cast_url": "https://farcaster.xyz/benido/0x7cde4360",
    "avg_score": "4.09"
  },
  {
    "author": "@satoushi",
    "author_url": "https://farcaster.xyz/satoushi",
    "casts": 1,
    "posts": 0,
    "comments": 1,
    "likes": 5,
    "recasts": 0,
    "replies": 3,
    "best_score": "5.10",
    "top_cast_url": "https://farcaster.xyz/satoushi/0xa56c1106",
    "avg_score": "5.10"
  },
  {
    "author": "@wellzy",
    "author_url": "https://farcaster.xyz/wellzy",
    "casts": 1,
    "posts": 0,
    "comments": 1,
    "likes": 5,
    "recasts": 0,
    "replies": 3,
    "best_score": "5.10",
    "top_cast_url": "https://farcaster.xyz/wellzy/0xe98efb5c",
    "avg_score": "5.10"
  },
  {
    "author": "@aeth44",
    "author_url": "https://farcaster.xyz/aeth44",
    "casts": 1,
    "posts": 0,
    "comments": 1,
    "likes": 5,
    "recasts": 1,
    "replies": 0,
    "best_score": "5.10",
    "top_cast_url": "https://farcaster.xyz/aeth44/0x244cce6b",
    "avg_score": "5.10"
  },
  {
    "author": "@badadvicehq",
    "author_url": "https://farcaster.xyz/badadvicehq",
    "casts": 1,
    "posts": 0,
    "comments": 1,
    "likes": 5,
    "recasts": 0,
    "replies": 1,
    "best_score": "5.10",
    "top_cast_url": "https://farcaster.xyz/badadvicehq/0xb206894f",
    "avg_score": "5.10"
  },
  {
    "author": "@ngmiai",
    "author_url": "https://farcaster.xyz/ngmiai",
    "casts": 1,
    "posts": 1,
    "comments": 0,
    "likes": 5,
    "recasts": 0,
    "replies": 0,
    "best_score": "5.10",
    "top_cast_url": "https://farcaster.xyz/ngmiai/0x650a65c8",
    "avg_score": "5.10"
  },
  {
    "author": "@maxdo",
    "author_url": "https://farcaster.xyz/maxdo",
    "casts": 1,
    "posts": 1,
    "comments": 0,
    "likes": 5,
    "recasts": 0,
    "replies": 1,
    "best_score": "5.10",
    "top_cast_url": "https://farcaster.xyz/maxdo/0x5a3a3e9c",
    "avg_score": "5.10"
  },
  {
    "author": "@gold-y",
    "author_url": "https://farcaster.xyz/gold-y",
    "casts": 1,
    "posts": 0,
    "comments": 1,
    "likes": 4,
    "recasts": 1,
    "replies": 3,
    "best_score": "4.68",
    "top_cast_url": "https://farcaster.xyz/gold-y/0xfb0eadd6",
    "avg_score": "4.68"
  },
  {
    "author": "@luciano",
    "author_url": "https://farcaster.xyz/luciano",
    "casts": 1,
    "posts": 0,
    "comments": 1,
    "likes": 4,
    "recasts": 0,
    "replies": 2,
    "best_score": "4.68",
    "top_cast_url": "https://farcaster.xyz/luciano/0x1411143a",
    "avg_score": "4.68"
  },
  {
    "author": "@penzlik",
    "author_url": "https://farcaster.xyz/penzlik",
    "casts": 1,
    "posts": 0,
    "comments": 1,
    "likes": 4,
    "recasts": 0,
    "replies": 1,
    "best_score": "4.68",
    "top_cast_url": "https://farcaster.xyz/penzlik/0xd0db3175",
    "avg_score": "4.68"
  },
  {
    "author": "@adexmakai",
    "author_url": "https://farcaster.xyz/adexmakai",
    "casts": 1,
    "posts": 1,
    "comments": 0,
    "likes": 4,
    "recasts": 0,
    "replies": 1,
    "best_score": "4.68",
    "top_cast_url": "https://farcaster.xyz/adexmakai/0x17130797",
    "avg_score": "4.68"
  },
  {
    "author": "@daikie",
    "author_url": "https://farcaster.xyz/daikie",
    "casts": 1,
    "posts": 1,
    "comments": 0,
    "likes": 4,
    "recasts": 0,
    "replies": 0,
    "best_score": "4.68",
    "top_cast_url": "https://farcaster.xyz/daikie/0x8cd69c1c",
    "avg_score": "4.68"
  },
  {
    "author": "@kenny",
    "author_url": "https://farcaster.xyz/kenny",
    "casts": 3,
    "posts": 0,
    "comments": 3,
    "likes": 4,
    "recasts": 0,
    "replies": 2,
    "best_score": "3.51",
    "top_cast_url": "https://farcaster.xyz/kenny/0x3f5b8bb3",
    "avg_score": "2.90"
  },
  {
    "author": "@thewisebull",
    "author_url": "https://farcaster.xyz/thewisebull",
    "casts": 2,
    "posts": 2,
    "comments": 0,
    "likes": 4,
    "recasts": 0,
    "replies": 2,
    "best_score": "3.51",
    "top_cast_url": "https://farcaster.xyz/thewisebull/0xd9b53525",
    "avg_score": "3.51"
  },
  {
    "author": "@kingjunaid12",
    "author_url": "https://farcaster.xyz/kingjunaid12",
    "casts": 1,
    "posts": 1,
    "comments": 0,
    "likes": 3,
    "recasts": 1,
    "replies": 2,
    "best_score": "4.17",
    "top_cast_url": "https://farcaster.xyz/kingjunaid12/0xb6da2005",
    "avg_score": "4.17"
  },
  {
    "author": "@bulldozer9",
    "author_url": "https://farcaster.xyz/bulldozer9",
    "casts": 1,
    "posts": 0,
    "comments": 1,
    "likes": 3,
    "recasts": 1,
    "replies": 3,
    "best_score": "4.17",
    "top_cast_url": "https://farcaster.xyz/bulldozer9/0x875bf31c",
    "avg_score": "4.17"
  },
  {
    "author": "@yodark",
    "author_url": "https://farcaster.xyz/yodark",
    "casts": 1,
    "posts": 0,
    "comments": 1,
    "likes": 3,
    "recasts": 1,
    "replies": 1,
    "best_score": "4.17",
    "top_cast_url": "https://farcaster.xyz/yodark/0x9084456d",
    "avg_score": "4.17"
  },
  {
    "author": "@dipedas",
    "author_url": "https://farcaster.xyz/dipedas",
    "casts": 1,
    "posts": 1,
    "comments": 0,
    "likes": 3,
    "recasts": 1,
    "replies": 1,
    "best_score": "4.17",
    "top_cast_url": "https://farcaster.xyz/dipedas/0x38e05e06",
    "avg_score": "4.17"
  },
  {
    "author": "@nextleveldarko",
    "author_url": "https://farcaster.xyz/nextleveldarko",
    "casts": 1,
    "posts": 0,
    "comments": 1,
    "likes": 3,
    "recasts": 0,
    "replies": 2,
    "best_score": "4.17",
    "top_cast_url": "https://farcaster.xyz/nextleveldarko/0xf4ba8cc2",
    "avg_score": "4.17"
  },
  {
    "author": "@shinmoma",
    "author_url": "https://farcaster.xyz/shinmoma",
    "casts": 1,
    "posts": 1,
    "comments": 0,
    "likes": 3,
    "recasts": 0,
    "replies": 1,
    "best_score": "4.17",
    "top_cast_url": "https://farcaster.xyz/shinmoma/0x0538b901",
    "avg_score": "4.17"
  },
  {
    "author": "@220",
    "author_url": "https://farcaster.xyz/220",
    "casts": 1,
    "posts": 1,
    "comments": 0,
    "likes": 3,
    "recasts": 0,
    "replies": 1,
    "best_score": "4.17",
    "top_cast_url": "https://farcaster.xyz/220/0x8a928554",
    "avg_score": "4.17"
  },
  {
    "author": "@sundoranth",
    "author_url": "https://farcaster.xyz/sundoranth",
    "casts": 1,
    "posts": 1,
    "comments": 0,
    "likes": 3,
    "recasts": 0,
    "replies": 1,
    "best_score": "4.17",
    "top_cast_url": "https://farcaster.xyz/sundoranth/0x65f73b82",
    "avg_score": "4.17"
  },
  {
    "author": "@milibooo",
    "author_url": "https://farcaster.xyz/milibooo",
    "casts": 1,
    "posts": 0,
    "comments": 1,
    "likes": 3,
    "recasts": 0,
    "replies": 1,
    "best_score": "4.17",
    "top_cast_url": "https://farcaster.xyz/milibooo/0x8ecb72d1",
    "avg_score": "4.17"
  },
  {
    "author": "@geisha",
    "author_url": "https://farcaster.xyz/geisha",
    "casts": 1,
    "posts": 0,
    "comments": 1,
    "likes": 3,
    "recasts": 0,
    "replies": 0,
    "best_score": "4.17",
    "top_cast_url": "https://farcaster.xyz/geisha/0x4b6ecb7c",
    "avg_score": "4.17"
  },
  {
    "author": "@neynar",
    "author_url": "https://farcaster.xyz/neynar",
    "casts": 2,
    "posts": 0,
    "comments": 2,
    "likes": 3,
    "recasts": 0,
    "replies": 4,
    "best_score": "3.51",
    "top_cast_url": "https://farcaster.xyz/neynar/0xada8e52b",
    "avg_score": "3.05"
  },
  {
    "author": "@shahbazbaaz",
    "author_url": "https://farcaster.xyz/shahbazbaaz",
    "casts": 2,
    "posts": 0,
    "comments": 2,
    "likes": 3,
    "recasts": 0,
    "replies": 2,
    "best_score": "3.51",
    "top_cast_url": "https://farcaster.xyz/shahbazbaaz/0x78a5efde",
    "avg_score": "3.05"
  },
  {
    "author": "@crazybowbot",
    "author_url": "https://farcaster.xyz/crazybowbot",
    "casts": 2,
    "posts": 2,
    "comments": 0,
    "likes": 2,
    "recasts": 0,
    "replies": 4,
    "best_score": "3.51",
    "top_cast_url": "https://farcaster.xyz/crazybowbot/0x11880961",
    "avg_score": "2.25"
  },
  {
    "author": "@azflin",
    "author_url": "https://farcaster.xyz/azflin",
    "casts": 1,
    "posts": 0,
    "comments": 1,
    "likes": 2,
    "recasts": 0,
    "replies": 2,
    "best_score": "3.51",
    "top_cast_url": "https://farcaster.xyz/azflin/0x8daf707b",
    "avg_score": "3.51"
  },
  {
    "author": "@yes2crypto",
    "author_url": "https://farcaster.xyz/yes2crypto",
    "casts": 1,
    "posts": 0,
    "comments": 1,
    "likes": 2,
    "recasts": 1,
    "replies": 1,
    "best_score": "3.51",
    "top_cast_url": "https://farcaster.xyz/yes2crypto/0x58155ae5",
    "avg_score": "3.51"
  },
  {
    "author": "@olystuart",
    "author_url": "https://farcaster.xyz/olystuart",
    "casts": 1,
    "posts": 0,
    "comments": 1,
    "likes": 2,
    "recasts": 0,
    "replies": 2,
    "best_score": "3.51",
    "top_cast_url": "https://farcaster.xyz/olystuart/0x815beabf",
    "avg_score": "3.51"
  },
  {
    "author": "@juniper",
    "author_url": "https://farcaster.xyz/juniper",
    "casts": 1,
    "posts": 0,
    "comments": 1,
    "likes": 2,
    "recasts": 0,
    "replies": 1,
    "best_score": "3.51",
    "top_cast_url": "https://farcaster.xyz/juniper/0x05048659",
    "avg_score": "3.51"
  },
  {
    "author": "@tako-unik",
    "author_url": "https://farcaster.xyz/tako-unik",
    "casts": 1,
    "posts": 0,
    "comments": 1,
    "likes": 2,
    "recasts": 0,
    "replies": 1,
    "best_score": "3.51",
    "top_cast_url": "https://farcaster.xyz/tako-unik/0x9a0760b6",
    "avg_score": "3.51"
  },
  {
    "author": "@adrianandreev",
    "author_url": "https://farcaster.xyz/adrianandreev",
    "casts": 1,
    "posts": 0,
    "comments": 1,
    "likes": 2,
    "recasts": 0,
    "replies": 0,
    "best_score": "3.51",
    "top_cast_url": "https://farcaster.xyz/adrianandreev/0x96276158",
    "avg_score": "3.51"
  },
  {
    "author": "@monteluna",
    "author_url": "https://farcaster.xyz/monteluna",
    "casts": 1,
    "posts": 0,
    "comments": 1,
    "likes": 2,
    "recasts": 0,
    "replies": 0,
    "best_score": "3.51",
    "top_cast_url": "https://farcaster.xyz/monteluna/0x68e86887",
    "avg_score": "3.51"
  },
  {
    "author": "@burrrrrberry",
    "author_url": "https://farcaster.xyz/burrrrrberry",
    "casts": 1,
    "posts": 0,
    "comments": 1,
    "likes": 2,
    "recasts": 0,
    "replies": 1,
    "best_score": "3.51",
    "top_cast_url": "https://farcaster.xyz/burrrrrberry/0x6c0e8b54",
    "avg_score": "3.51"
  },
  {
    "author": "@shifat007",
    "author_url": "https://farcaster.xyz/shifat007",
    "casts": 1,
    "posts": 1,
    "comments": 0,
    "likes": 2,
    "recasts": 0,
    "replies": 1,
    "best_score": "3.51",
    "top_cast_url": "https://farcaster.xyz/shifat007/0xeab9570b",
    "avg_score": "3.51"
  },
  {
    "author": "@alauddin35",
    "author_url": "https://farcaster.xyz/alauddin35",
    "casts": 1,
    "posts": 0,
    "comments": 1,
    "likes": 2,
    "recasts": 1,
    "replies": 0,
    "best_score": "3.51",
    "top_cast_url": "https://farcaster.xyz/alauddin35/0x9bedb92c",
    "avg_score": "3.51"
  },
  {
    "author": "@maxximillian",
    "author_url": "https://farcaster.xyz/maxximillian",
    "casts": 1,
    "posts": 0,
    "comments": 1,
    "likes": 2,
    "recasts": 0,
    "replies": 0,
    "best_score": "3.51",
    "top_cast_url": "https://farcaster.xyz/maxximillian/0x39155f7a",
    "avg_score": "3.51"
  },
  {
    "author": "@lutik",
    "author_url": "https://farcaster.xyz/lutik",
    "casts": 1,
    "posts": 1,
    "comments": 0,
    "likes": 2,
    "recasts": 0,
    "replies": 0,
    "best_score": "3.51",
    "top_cast_url": "https://farcaster.xyz/lutik/0x221e9d5c",
    "avg_score": "3.51"
  },
  {
    "author": "@agrimony",
    "author_url": "https://farcaster.xyz/agrimony",
    "casts": 1,
    "posts": 0,
    "comments": 1,
    "likes": 2,
    "recasts": 0,
    "replies": 0,
    "best_score": "3.51",
    "top_cast_url": "https://farcaster.xyz/agrimony/0xb7c68c74",
    "avg_score": "3.51"
  },
  {
    "author": "@and42",
    "author_url": "https://farcaster.xyz/and42",
    "casts": 1,
    "posts": 0,
    "comments": 1,
    "likes": 2,
    "recasts": 0,
    "replies": 0,
    "best_score": "3.51",
    "top_cast_url": "https://farcaster.xyz/and42/0xa55cd655",
    "avg_score": "3.51"
  },
  {
    "author": "@mikapro",
    "author_url": "https://farcaster.xyz/mikapro",
    "casts": 3,
    "posts": 0,
    "comments": 3,
    "likes": 2,
    "recasts": 0,
    "replies": 4,
    "best_score": "2.59",
    "top_cast_url": "https://farcaster.xyz/mikapro/0xba500f7a",
    "avg_score": "2.06"
  },
  {
    "author": "@crraihan",
    "author_url": "https://farcaster.xyz/crraihan",
    "casts": 3,
    "posts": 2,
    "comments": 1,
    "likes": 2,
    "recasts": 0,
    "replies": 1,
    "best_score": "2.59",
    "top_cast_url": "https://farcaster.xyz/crraihan/0x49e98b05",
    "avg_score": "2.06"
  },
  {
    "author": "@annie-45",
    "author_url": "https://farcaster.xyz/annie-45",
    "casts": 2,
    "posts": 0,
    "comments": 2,
    "likes": 2,
    "recasts": 0,
    "replies": 4,
    "best_score": "2.59",
    "top_cast_url": "https://farcaster.xyz/annie-45/0xd7ffc7ea",
    "avg_score": "2.59"
  },
  {
    "author": "@aram18",
    "author_url": "https://farcaster.xyz/aram18",
    "casts": 2,
    "posts": 1,
    "comments": 1,
    "likes": 2,
    "recasts": 0,
    "replies": 2,
    "best_score": "2.59",
    "top_cast_url": "https://farcaster.xyz/aram18/0xa54a0e5c",
    "avg_score": "2.59"
  },
  {
    "author": "@duggu.base.eth",
    "author_url": "https://farcaster.xyz/duggu.base.eth",
    "casts": 2,
    "posts": 0,
    "comments": 2,
    "likes": 2,
    "recasts": 0,
    "replies": 0,
    "best_score": "2.59",
    "top_cast_url": "https://farcaster.xyz/duggu.base.eth/0x0a51bb97",
    "avg_score": "2.59"
  },
  {
    "author": "@dhudhu",
    "author_url": "https://farcaster.xyz/dhudhu",
    "casts": 2,
    "posts": 2,
    "comments": 0,
    "likes": 1,
    "recasts": 0,
    "replies": 2,
    "best_score": "2.59",
    "top_cast_url": "https://farcaster.xyz/dhudhu/0x0934b4a0",
    "avg_score": "1.79"
  },
  {
    "author": "@richieboston",
    "author_url": "https://farcaster.xyz/richieboston",
    "casts": 1,
    "posts": 0,
    "comments": 1,
    "likes": 1,
    "recasts": 0,
    "replies": 4,
    "best_score": "2.59",
    "top_cast_url": "https://farcaster.xyz/richieboston/0xb030370f",
    "avg_score": "2.59"
  },
  {
    "author": "@six",
    "author_url": "https://farcaster.xyz/six",
    "casts": 1,
    "posts": 0,
    "comments": 1,
    "likes": 1,
    "recasts": 0,
    "replies": 2,
    "best_score": "2.59",
    "top_cast_url": "https://farcaster.xyz/six/0x8cc3e5d7",
    "avg_score": "2.59"
  },
  {
    "author": "@koss-hilll.base.eth",
    "author_url": "https://farcaster.xyz/koss-hilll.base.eth",
    "casts": 1,
    "posts": 1,
    "comments": 0,
    "likes": 1,
    "recasts": 0,
    "replies": 2,
    "best_score": "2.59",
    "top_cast_url": "https://farcaster.xyz/koss-hilll.base.eth/0x79fc147d",
    "avg_score": "2.59"
  },
  {
    "author": "@fabfour",
    "author_url": "https://farcaster.xyz/fabfour",
    "casts": 1,
    "posts": 1,
    "comments": 0,
    "likes": 1,
    "recasts": 0,
    "replies": 3,
    "best_score": "2.59",
    "top_cast_url": "https://farcaster.xyz/fabfour/0x8d1d97e9",
    "avg_score": "2.59"
  },
  {
    "author": "@katkartel",
    "author_url": "https://farcaster.xyz/katkartel",
    "casts": 1,
    "posts": 0,
    "comments": 1,
    "likes": 1,
    "recasts": 0,
    "replies": 1,
    "best_score": "2.59",
    "top_cast_url": "https://farcaster.xyz/katkartel/0x7ddb390b",
    "avg_score": "2.59"
  },
  {
    "author": "@strangesmell",
    "author_url": "https://farcaster.xyz/strangesmell",
    "casts": 1,
    "posts": 0,
    "comments": 1,
    "likes": 1,
    "recasts": 0,
    "replies": 1,
    "best_score": "2.59",
    "top_cast_url": "https://farcaster.xyz/strangesmell/0x02a045d3",
    "avg_score": "2.59"
  },
  {
    "author": "@slimeasydizzy499.base.eth",
    "author_url": "https://farcaster.xyz/slimeasydizzy499.base.eth",
    "casts": 1,
    "posts": 1,
    "comments": 0,
    "likes": 1,
    "recasts": 0,
    "replies": 1,
    "best_score": "2.59",
    "top_cast_url": "https://farcaster.xyz/slimeasydizzy499.base.eth/0x622c661a",
    "avg_score": "2.59"
  },
  {
    "author": "@pmayr",
    "author_url": "https://farcaster.xyz/pmayr",
    "casts": 1,
    "posts": 0,
    "comments": 1,
    "likes": 1,
    "recasts": 0,
    "replies": 2,
    "best_score": "2.59",
    "top_cast_url": "https://farcaster.xyz/pmayr/0xa3f93e54",
    "avg_score": "2.59"
  },
  {
    "author": "@moonofficial",
    "author_url": "https://farcaster.xyz/moonofficial",
    "casts": 1,
    "posts": 0,
    "comments": 1,
    "likes": 1,
    "recasts": 0,
    "replies": 1,
    "best_score": "2.59",
    "top_cast_url": "https://farcaster.xyz/moonofficial/0x90f80127",
    "avg_score": "2.59"
  },
  {
    "author": "@yogendrapatel007",
    "author_url": "https://farcaster.xyz/yogendrapatel007",
    "casts": 1,
    "posts": 1,
    "comments": 0,
    "likes": 1,
    "recasts": 0,
    "replies": 1,
    "best_score": "2.59",
    "top_cast_url": "https://farcaster.xyz/yogendrapatel007/0x0ec47dbe",
    "avg_score": "2.59"
  },
  {
    "author": "@shahrokhpower",
    "author_url": "https://farcaster.xyz/shahrokhpower",
    "casts": 1,
    "posts": 1,
    "comments": 0,
    "likes": 1,
    "recasts": 1,
    "replies": 0,
    "best_score": "2.59",
    "top_cast_url": "https://farcaster.xyz/shahrokhpower/0xef5a5b66",
    "avg_score": "2.59"
  },
  {
    "author": "@feronai",
    "author_url": "https://farcaster.xyz/feronai",
    "casts": 1,
    "posts": 0,
    "comments": 1,
    "likes": 1,
    "recasts": 0,
    "replies": 1,
    "best_score": "2.59",
    "top_cast_url": "https://farcaster.xyz/feronai/0x4312c815",
    "avg_score": "2.59"
  },
  {
    "author": "@retrojoystick",
    "author_url": "https://farcaster.xyz/retrojoystick",
    "casts": 1,
    "posts": 0,
    "comments": 1,
    "likes": 1,
    "recasts": 0,
    "replies": 1,
    "best_score": "2.59",
    "top_cast_url": "https://farcaster.xyz/retrojoystick/0xde6c4c8d",
    "avg_score": "2.59"
  },
  {
    "author": "@abubakerjameel",
    "author_url": "https://farcaster.xyz/abubakerjameel",
    "casts": 1,
    "posts": 0,
    "comments": 1,
    "likes": 1,
    "recasts": 0,
    "replies": 1,
    "best_score": "2.59",
    "top_cast_url": "https://farcaster.xyz/abubakerjameel/0x9b8c3acc",
    "avg_score": "2.59"
  },
  {
    "author": "@sayangel",
    "author_url": "https://farcaster.xyz/sayangel",
    "casts": 1,
    "posts": 0,
    "comments": 1,
    "likes": 1,
    "recasts": 0,
    "replies": 1,
    "best_score": "2.59",
    "top_cast_url": "https://farcaster.xyz/sayangel/0x7ce1c485",
    "avg_score": "2.59"
  },
  {
    "author": "@suryaprakash",
    "author_url": "https://farcaster.xyz/suryaprakash",
    "casts": 1,
    "posts": 1,
    "comments": 0,
    "likes": 1,
    "recasts": 0,
    "replies": 0,
    "best_score": "2.59",
    "top_cast_url": "https://farcaster.xyz/suryaprakash/0x26fc0e51",
    "avg_score": "2.59"
  },
  {
    "author": "@deepu552000",
    "author_url": "https://farcaster.xyz/deepu552000",
    "casts": 1,
    "posts": 1,
    "comments": 0,
    "likes": 1,
    "recasts": 0,
    "replies": 1,
    "best_score": "2.59",
    "top_cast_url": "https://farcaster.xyz/deepu552000/0x7674a4fd",
    "avg_score": "2.59"
  },
  {
    "author": "@zaal",
    "author_url": "https://farcaster.xyz/zaal",
    "casts": 1,
    "posts": 0,
    "comments": 1,
    "likes": 1,
    "recasts": 0,
    "replies": 1,
    "best_score": "2.59",
    "top_cast_url": "https://farcaster.xyz/zaal/0x109477b7",
    "avg_score": "2.59"
  },
  {
    "author": "@teberen",
    "author_url": "https://farcaster.xyz/teberen",
    "casts": 1,
    "posts": 1,
    "comments": 0,
    "likes": 1,
    "recasts": 1,
    "replies": 0,
    "best_score": "2.59",
    "top_cast_url": "https://farcaster.xyz/teberen/0xbb960db8",
    "avg_score": "2.59"
  },
  {
    "author": "@j-valeska",
    "author_url": "https://farcaster.xyz/j-valeska",
    "casts": 1,
    "posts": 0,
    "comments": 1,
    "likes": 1,
    "recasts": 0,
    "replies": 1,
    "best_score": "2.59",
    "top_cast_url": "https://farcaster.xyz/j-valeska/0x594cb93f",
    "avg_score": "2.59"
  },
  {
    "author": "@mahdijnt",
    "author_url": "https://farcaster.xyz/mahdijnt",
    "casts": 1,
    "posts": 0,
    "comments": 1,
    "likes": 1,
    "recasts": 0,
    "replies": 1,
    "best_score": "2.59",
    "top_cast_url": "https://farcaster.xyz/mahdijnt/0x9872a3db",
    "avg_score": "2.59"
  },
  {
    "author": "@gaspardguerre",
    "author_url": "https://farcaster.xyz/gaspardguerre",
    "casts": 1,
    "posts": 1,
    "comments": 0,
    "likes": 1,
    "recasts": 0,
    "replies": 0,
    "best_score": "2.59",
    "top_cast_url": "https://farcaster.xyz/gaspardguerre/0x27cc13d8",
    "avg_score": "2.59"
  },
  {
    "author": "@bu9ape",
    "author_url": "https://farcaster.xyz/bu9ape",
    "casts": 1,
    "posts": 1,
    "comments": 0,
    "likes": 1,
    "recasts": 1,
    "replies": 0,
    "best_score": "2.59",
    "top_cast_url": "https://farcaster.xyz/bu9ape/0x772767ec",
    "avg_score": "2.59"
  },
  {
    "author": "@helladj",
    "author_url": "https://farcaster.xyz/helladj",
    "casts": 1,
    "posts": 1,
    "comments": 0,
    "likes": 1,
    "recasts": 0,
    "replies": 0,
    "best_score": "2.59",
    "top_cast_url": "https://farcaster.xyz/helladj/0x4b13e8aa",
    "avg_score": "2.59"
  },
  {
    "author": "@strictlysave",
    "author_url": "https://farcaster.xyz/strictlysave",
    "casts": 1,
    "posts": 0,
    "comments": 1,
    "likes": 1,
    "recasts": 0,
    "replies": 0,
    "best_score": "2.59",
    "top_cast_url": "https://farcaster.xyz/strictlysave/0x9f931378",
    "avg_score": "2.59"
  }
]
