[
  {
    "author": "@six",
    "author_url": "https://farcaster.xyz/six",
    "casts": 1,
    "posts": 1,
    "comments": 0,
    "likes": 28,
    "recasts": 4,
    "replies": 1,
    "best_score": "8.71",
    "top_cast_url": "https://farcaster.xyz/six/0x3eae003f",
    "avg_score": "8.71"
  },
  {
    "author": "@nounishprof",
    "author_url": "https://farcaster.xyz/nounishprof",
    "casts": 1,
    "posts": 0,
    "comments": 1,
    "likes": 18,
    "recasts": 3,
    "replies": 4,
    "best_score": "7.74",
    "top_cast_url": "https://farcaster.xyz/nounishprof/0x94d88d89",
    "avg_score": "7.74"
  },
  {
    "author": "@evolve",
    "author_url": "https://farcaster.xyz/evolve",
    "casts": 1,
    "posts": 0,
    "comments": 1,
    "likes": 14,
    "recasts": 3,
    "replies": 7,
    "best_score": "7.20",
    "top_cast_url": "https://farcaster.xyz/evolve/0xcec15b4e",
    "avg_score": "7.20"
  },
  {
    "author": "@pinklady77",
    "author_url": "https://farcaster.xyz/pinklady77",
    "casts": 1,
    "posts": 1,
    "comments": 0,
    "likes": 14,
    "recasts": 1,
    "replies": 4,
    "best_score": "7.20",
    "top_cast_url": "https://farcaster.xyz/pinklady77/0x74b17ad8",
    "avg_score": "7.20"
  },
  {
    "author": "@denizakar",
    "author_url": "https://farcaster.xyz/denizakar",
    "casts": 1,
    "posts": 1,
    "comments": 0,
    "likes": 7,
    "recasts": 0,
    "replies": 3,
    "best_score": "5.76",
    "top_cast_url": "https://farcaster.xyz/denizakar/0xd47b6faa",
    "avg_score": "5.76"
  },
  {
    "author": "@ogerpon",
    "author_url": "https://farcaster.xyz/ogerpon",
    "casts": 2,
    "posts": 0,
    "comments": 2,
    "likes": 7,
    "recasts": 0,
    "replies": 1,
    "best_score": "4.68",
    "top_cast_url": "https://farcaster.xyz/ogerpon/0x5c8487ef",
    "avg_score": "4.42"
  },
  {
    "author": "@kenny",
    "author_url": "https://farcaster.xyz/kenny",
    "casts": 3,
    "posts": 0,
    "comments": 3,
    "likes": 6,
    "recasts": 0,
    "replies": 5,
    "best_score": "4.68",
    "top_cast_url": "https://farcaster.xyz/kenny/0xc562b07b",
    "avg_score": "3.06"
  },
  {
    "author": "@crazybowbot",
    "author_url": "https://farcaster.xyz/crazybowbot",
    "casts": 3,
    "posts": 3,
    "comments": 0,
    "likes": 6,
    "recasts": 1,
    "replies": 0,
    "best_score": "4.17",
    "top_cast_url": "https://farcaster.xyz/crazybowbot/0x0620e7b8",
    "avg_score": "3.42"
  },
  {
    "author": "@paragraph",
    "author_url": "https://farcaster.xyz/paragraph",
    "casts": 1,
    "posts": 1,
    "comments": 0,
    "likes": 4,
    "recasts": 2,
    "replies": 0,
    "best_score": "4.68",
    "top_cast_url": "https://farcaster.xyz/paragraph/0x6429d1a0",
    "avg_score": "4.68"
  },
  {
    "author": "@peykan57",
    "author_url": "https://farcaster.xyz/peykan57",
    "casts": 1,
    "posts": 1,
    "comments": 0,
    "likes": 4,
    "recasts": 0,
    "replies": 0,
    "best_score": "4.68",
    "top_cast_url": "https://farcaster.xyz/peykan57/0x58e3e3a3",
    "avg_score": "4.68"
  },
  {
    "author": "@muhammadind",
    "author_url": "https://farcaster.xyz/muhammadind",
    "casts": 1,
    "posts": 0,
    "comments": 1,
    "likes": 4,
    "recasts": 0,
    "replies": 0,
    "best_score": "4.68",
    "top_cast_url": "https://farcaster.xyz/muhammadind/0xc497feb0",
    "avg_score": "4.68"
  },
  {
    "author": "@mikapro",
    "author_url": "https://farcaster.xyz/mikapro",
    "casts": 3,
    "posts": 0,
    "comments": 3,
    "likes": 4,
    "recasts": 0,
    "replies": 3,
    "best_score": "3.51",
    "top_cast_url": "https://farcaster.xyz/mikapro/0x5cfd74d5",
    "avg_score": "2.90"
  },
  {
    "author": "@akela113",
    "author_url": "https://farcaster.xyz/akela113",
    "casts": 3,
    "posts": 0,
    "comments": 3,
    "likes": 3,
    "recasts": 0,
    "replies": 0,
    "best_score": "2.59",
    "top_cast_url": "https://farcaster.xyz/akela113/0x96a02bab",
    "avg_score": "2.59"
  },
  {
    "author": "@ezincrypto",
    "author_url": "https://farcaster.xyz/ezincrypto",
    "casts": 1,
    "posts": 0,
    "comments": 1,
    "likes": 2,
    "recasts": 0,
    "replies": 1,
    "best_score": "3.51",
    "top_cast_url": "https://farcaster.xyz/ezincrypto/0xce823be5",
    "avg_score": "3.51"
  },
  {
    "author": "@mrsohag",
    "author_url": "https://farcaster.xyz/mrsohag",
    "casts": 1,
    "posts": 1,
    "comments": 0,
    "likes": 2,
    "recasts": 0,
    "replies": 1,
    "best_score": "3.51",
    "top_cast_url": "https://farcaster.xyz/mrsohag/0xfecef7fa",
    "avg_score": "3.51"
  },
  {
    "author": "@unimog",
    "author_url": "https://farcaster.xyz/unimog",
    "casts": 1,
    "posts": 1,
    "comments": 0,
    "likes": 2,
    "recasts": 0,
    "replies": 2,
    "best_score": "3.51",
    "top_cast_url": "https://farcaster.xyz/unimog/0x55b93c62",
    "avg_score": "3.51"
  },
  {
    "author": "@nickysap",
    "author_url": "https://farcaster.xyz/nickysap",
    "casts": 1,
    "posts": 0,
    "comments": 1,
    "likes": 2,
    "recasts": 0,
    "replies": 0,
    "best_score": "3.51",
    "top_cast_url": "https://farcaster.xyz/nickysap/0x5a8bda4d",
    "avg_score": "3.51"
  },
  {
    "author": "@bbthrntn",
    "author_url": "https://farcaster.xyz/bbthrntn",
    "casts": 1,
    "posts": 0,
    "comments": 1,
    "likes": 2,
    "recasts": 0,
    "replies": 0,
    "best_score": "3.51",
    "top_cast_url": "https://farcaster.xyz/bbthrntn/0x0d7a01ef",
    "avg_score": "3.51"
  },
  {
    "author": "@ogg",
    "author_url": "https://farcaster.xyz/ogg",
    "casts": 1,
    "posts": 0,
    "comments": 1,
    "likes": 2,
    "recasts": 0,
    "replies": 0,
    "best_score": "3.51",
    "top_cast_url": "https://farcaster.xyz/ogg/0x4e18b1f3",
    "avg_score": "3.51"
  },
  {
    "author": "@ds8",
    "author_url": "https://farcaster.xyz/ds8",
    "casts": 1,
    "posts": 0,
    "comments": 1,
    "likes": 2,
    "recasts": 0,
    "replies": 0,
    "best_score": "3.51",
    "top_cast_url": "https://farcaster.xyz/ds8/0xe6029e81",
    "avg_score": "3.51"
  },
  {
    "author": "@raviku",
    "author_url": "https://farcaster.xyz/raviku",
    "casts": 2,
    "posts": 2,
    "comments": 0,
    "likes": 2,
    "recasts": 0,
    "replies": 0,
    "best_score": "2.59",
    "top_cast_url": "https://farcaster.xyz/raviku/0xa744b26d",
    "avg_score": "2.59"
  },
  {
    "author": "@gorhionolo",
    "author_url": "https://farcaster.xyz/gorhionolo",
    "casts": 2,
    "posts": 0,
    "comments": 2,
    "likes": 2,
    "recasts": 0,
    "replies": 2,
    "best_score": "2.59",
    "top_cast_url": "https://farcaster.xyz/gorhionolo/0xf1aaedb7",
    "avg_score": "2.59"
  },
  {
    "author": "@mypokerofff",
    "author_url": "https://farcaster.xyz/mypokerofff",
    "casts": 2,
    "posts": 0,
    "comments": 2,
    "likes": 2,
    "recasts": 0,
    "replies": 1,
    "best_score": "2.59",
    "top_cast_url": "https://farcaster.xyz/mypokerofff/0xa13cdd5a",
    "avg_score": "2.59"
  },
  {
    "author": "@joysender",
    "author_url": "https://farcaster.xyz/joysender",
    "casts": 1,
    "posts": 1,
    "comments": 0,
    "likes": 1,
    "recasts": 0,
    "replies": 7,
    "best_score": "2.59",
    "top_cast_url": "https://farcaster.xyz/joysender/0x313597a4",
    "avg_score": "2.59"
  },
  {
    "author": "@thejohnnycrypto",
    "author_url": "https://farcaster.xyz/thejohnnycrypto",
    "casts": 1,
    "posts": 0,
    "comments": 1,
    "likes": 1,
    "recasts": 0,
    "replies": 1,
    "best_score": "2.59",
    "top_cast_url": "https://farcaster.xyz/thejohnnycrypto/0x3e767db5",
    "avg_score": "2.59"
  },
  {
    "author": "@kcrypto",
    "author_url": "https://farcaster.xyz/kcrypto",
    "casts": 1,
    "posts": 0,
    "comments": 1,
    "likes": 1,
    "recasts": 0,
    "replies": 1,
    "best_score": "2.59",
    "top_cast_url": "https://farcaster.xyz/kcrypto/0xc9fb6bc8",
    "avg_score": "2.59"
  },
  {
    "author": "@shabuzaman",
    "author_url": "https://farcaster.xyz/shabuzaman",
    "casts": 1,
    "posts": 0,
    "comments": 1,
    "likes": 1,
    "recasts": 0,
    "replies": 1,
    "best_score": "2.59",
    "top_cast_url": "https://farcaster.xyz/shabuzaman/0x1867c3d0",
    "avg_score": "2.59"
  },
  {
    "author": "@adam-",
    "author_url": "https://farcaster.xyz/adam-",
    "casts": 1,
    "posts": 0,
    "comments": 1,
    "likes": 1,
    "recasts": 0,
    "replies": 1,
    "best_score": "2.59",
    "top_cast_url": "https://farcaster.xyz/adam-/0x74234756",
    "avg_score": "2.59"
  },
  {
    "author": "@g4mer15",
    "author_url": "https://farcaster.xyz/g4mer15",
    "casts": 1,
    "posts": 0,
    "comments": 1,
    "likes": 1,
    "recasts": 0,
    "replies": 0,
    "best_score": "2.59",
    "top_cast_url": "https://farcaster.xyz/g4mer15/0xab43df73",
    "avg_score": "2.59"
  },
  {
    "author": "@lefterisjp",
    "author_url": "https://farcaster.xyz/lefterisjp",
    "casts": 1,
    "posts": 0,
    "comments": 1,
    "likes": 1,
    "recasts": 0,
    "replies": 0,
    "best_score": "2.59",
    "top_cast_url": "https://farcaster.xyz/lefterisjp/0xe7980433",
    "avg_score": "2.59"
  },
  {
    "author": "@adrijan",
    "author_url": "https://farcaster.xyz/adrijan",
    "casts": 1,
    "posts": 1,
    "comments": 0,
    "likes": 1,
    "recasts": 0,
    "replies": 0,
    "best_score": "2.59",
    "top_cast_url": "https://farcaster.xyz/adrijan/0xfeb51bba",
    "avg_score": "2.59"
  },
  {
    "author": "@stultulo",
    "author_url": "https://farcaster.xyz/stultulo",
    "casts": 1,
    "posts": 1,
    "comments": 0,
    "likes": 1,
    "recasts": 0,
    "replies": 0,
    "best_score": "2.59",
    "top_cast_url": "https://farcaster.xyz/stultulo/0x09684af0",
    "avg_score": "2.59"
  },
  {
    "author": "@cryptosovereign",
    "author_url": "https://farcaster.xyz/cryptosovereign",
    "casts": 1,
    "posts": 1,
    "comments": 0,
    "likes": 1,
    "recasts": 0,
    "replies": 1,
    "best_score": "2.59",
    "top_cast_url": "https://farcaster.xyz/cryptosovereign/0x5c1b3dff",
    "avg_score": "2.59"
  },
  {
    "author": "@bitswagger",
    "author_url": "https://farcaster.xyz/bitswagger",
    "casts": 1,
    "posts": 1,
    "comments": 0,
    "likes": 1,
    "recasts": 0,
    "replies": 0,
    "best_score": "2.59",
    "top_cast_url": "https://farcaster.xyz/bitswagger/0x23b7e588",
    "avg_score": "2.59"
  },
  {
    "author": "@teberen",
    "author_url": "https://farcaster.xyz/teberen",
    "casts": 1,
    "posts": 1,
    "comments": 0,
    "likes": 1,
    "recasts": 0,
    "replies": 0,
    "best_score": "2.59",
    "top_cast_url": "https://farcaster.xyz/teberen/0x01e5f7ab",
    "avg_score": "2.59"
  },
  {
    "author": "@noxfonos",
    "author_url": "https://farcaster.xyz/noxfonos",
    "casts": 1,
    "posts": 1,
    "comments": 0,
    "likes": 1,
    "recasts": 1,
    "replies": 0,
    "best_score": "2.59",
    "top_cast_url": "https://farcaster.xyz/noxfonos/0x82b973ab",
    "avg_score": "2.59"
  },
  {
    "author": "@mizages",
    "author_url": "https://farcaster.xyz/mizages",
    "casts": 1,
    "posts": 0,
    "comments": 1,
    "likes": 1,
    "recasts": 0,
    "replies": 0,
    "best_score": "2.59",
    "top_cast_url": "https://farcaster.xyz/mizages/0xef0ab436",
    "avg_score": "2.59"
  },
  {
    "author": "@bigtone",
    "author_url": "https://farcaster.xyz/bigtone",
    "casts": 1,
    "posts": 1,
    "comments": 0,
    "likes": 1,
    "recasts": 0,
    "replies": 0,
    "best_score": "2.59",
    "top_cast_url": "https://farcaster.xyz/bigtone/0x451d1869",
    "avg_score": "2.59"
  },
  {
    "author": "@11031988ano",
    "author_url": "https://farcaster.xyz/11031988ano",
    "casts": 1,
    "posts": 0,
    "comments": 1,
    "likes": 1,
    "recasts": 1,
    "replies": 0,
    "best_score": "2.59",
    "top_cast_url": "https://farcaster.xyz/11031988ano/0x609b737f",
    "avg_score": "2.59"
  },
  {
    "author": "@amircrypto82",
    "author_url": "https://farcaster.xyz/amircrypto82",
    "casts": 1,
    "posts": 1,
    "comments": 0,
    "likes": 1,
    "recasts": 0,
    "replies": 0,
    "best_score": "2.59",
    "top_cast_url": "https://farcaster.xyz/amircrypto82/0xb8503b64",
    "avg_score": "2.59"
  },
  {
    "author": "@akhyari",
    "author_url": "https://farcaster.xyz/akhyari",
    "casts": 1,
    "posts": 0,
    "comments": 1,
    "likes": 1,
    "recasts": 0,
    "replies": 0,
    "best_score": "2.59",
    "top_cast_url": "https://farcaster.xyz/akhyari/0xff1947e0",
    "avg_score": "2.59"
  },
  {
    "author": "@and42",
    "author_url": "https://farcaster.xyz/and42",
    "casts": 1,
    "posts": 0,
    "comments": 1,
    "likes": 1,
    "recasts": 0,
    "replies": 0,
    "best_score": "2.59",
    "top_cast_url": "https://farcaster.xyz/and42/0xb83d64e6",
    "avg_score": "2.59"
  },
  {
    "author": "@eddweather",
    "author_url": "https://farcaster.xyz/eddweather",
    "casts": 1,
    "posts": 0,
    "comments": 1,
    "likes": 1,
    "recasts": 0,
    "replies": 0,
    "best_score": "2.59",
    "top_cast_url": "https://farcaster.xyz/eddweather/0x3b4ffe6b",
    "avg_score": "2.59"
  },
  {
    "author": "@framedl",
    "author_url": "https://farcaster.xyz/framedl",
    "casts": 1,
    "posts": 0,
    "comments": 1,
    "likes": 1,
    "recasts": 0,
    "replies": 0,
    "best_score": "2.59",
    "top_cast_url": "https://farcaster.xyz/framedl/0xeac98ba8",
    "avg_score": "2.59"
  },
  {
    "author": "@220",
    "author_url": "https://farcaster.xyz/220",
    "casts": 1,
    "posts": 0,
    "comments": 1,
    "likes": 1,
    "recasts": 0,
    "replies": 0,
    "best_score": "2.59",
    "top_cast_url": "https://farcaster.xyz/220/0x7d1bdb18",
    "avg_score": "2.59"
  },
  {
    "author": "@maximthuhalko",
    "author_url": "https://farcaster.xyz/maximthuhalko",
    "casts": 1,
    "posts": 0,
    "comments": 1,
    "likes": 1,
    "recasts": 0,
    "replies": 0,
    "best_score": "2.59",
    "top_cast_url": "https://farcaster.xyz/maximthuhalko/0x32550263",
    "avg_score": "2.59"
  },
  {
    "author": "@mevsme",
    "author_url": "https://farcaster.xyz/mevsme",
    "casts": 2,
    "posts": 2,
    "comments": 0,
    "likes": 0,
    "recasts": 0,
    "replies": 2,
    "best_score": "1.00",
    "top_cast_url": "https://farcaster.xyz/mevsme/0x56ef46bc",
    "avg_score": "1.00"
  },
  {
    "author": "@pritom626",
    "author_url": "https://farcaster.xyz/pritom626",
    "casts": 1,
    "posts": 1,
    "comments": 0,
    "likes": 0,
    "recasts": 0,
    "replies": 2,
    "best_score": "1.00",
    "top_cast_url": "https://farcaster.xyz/pritom626/0x9ed87052",
    "avg_score": "1.00"
  },
  {
    "author": "@ahsenkhan",
    "author_url": "https://farcaster.xyz/ahsenkhan",
    "casts": 1,
    "posts": 1,
    "comments": 0,
    "likes": 0,
    "recasts": 0,
    "replies": 1,
    "best_score": "1.00",
    "top_cast_url": "https://farcaster.xyz/ahsenkhan/0xa9e64041",
    "avg_score": "1.00"
  },
  {
    "author": "@sserssergesserss",
    "author_url": "https://farcaster.xyz/sserssergesserss",
    "casts": 1,
    "posts": 1,
    "comments": 0,
    "likes": 0,
    "recasts": 0,
    "replies": 1,
    "best_score": "1.00",
    "top_cast_url": "https://farcaster.xyz/sserssergesserss/0xe64de501",
    "avg_score": "1.00"
  },
  {
    "author": "@fkaany",
    "author_url": "https://farcaster.xyz/fkaany",
    "casts": 1,
    "posts": 0,
    "comments": 1,
    "likes": 0,
    "recasts": 0,
    "replies": 1,
    "best_score": "1.00",
    "top_cast_url": "https://farcaster.xyz/fkaany/0x53420c6e",
    "avg_score": "1.00"
  },
  {
    "author": "@pollodotlol",
    "author_url": "https://farcaster.xyz/pollodotlol",
    "casts": 1,
    "posts": 1,
    "comments": 0,
    "likes": 0,
    "recasts": 0,
    "replies": 1,
    "best_score": "1.00",
    "top_cast_url": "https://farcaster.xyz/pollodotlol/0x1fc48a10",
    "avg_score": "1.00"
  },
  {
    "author": "@zenscopelab.base.eth",
    "author_url": "https://farcaster.xyz/zenscopelab.base.eth",
    "casts": 1,
    "posts": 1,
    "comments": 0,
    "likes": 0,
    "recasts": 0,
    "replies": 1,
    "best_score": "1.00",
    "top_cast_url": "https://farcaster.xyz/zenscopelab.base.eth/0x57721503",
    "avg_score": "1.00"
  },
  {
    "author": "@vidalor.base.eth",
    "author_url": "https://farcaster.xyz/vidalor.base.eth",
    "casts": 1,
    "posts": 1,
    "comments": 0,
    "likes": 0,
    "recasts": 0,
    "replies": 1,
    "best_score": "1.00",
    "top_cast_url": "https://farcaster.xyz/vidalor.base.eth/0x1afa7a02",
    "avg_score": "1.00"
  },
  {
    "author": "@echos-whisper",
    "author_url": "https://farcaster.xyz/echos-whisper",
    "casts": 1,
    "posts": 1,
    "comments": 0,
    "likes": 0,
    "recasts": 0,
    "replies": 2,
    "best_score": "1.00",
    "top_cast_url": "https://farcaster.xyz/echos-whisper/0x0d6bf96b",
    "avg_score": "1.00"
  },
  {
    "author": "@elaspri",
    "author_url": "https://farcaster.xyz/elaspri",
    "casts": 1,
    "posts": 0,
    "comments": 1,
    "likes": 0,
    "recasts": 0,
    "replies": 1,
    "best_score": "1.00",
    "top_cast_url": "https://farcaster.xyz/elaspri/0x11ad4052",
    "avg_score": "1.00"
  },
  {
    "author": "@pmfi",
    "author_url": "https://farcaster.xyz/pmfi",
    "casts": 1,
    "posts": 1,
    "comments": 0,
    "likes": 0,
    "recasts": 1,
    "replies": 0,
    "best_score": "1.00",
    "top_cast_url": "https://farcaster.xyz/pmfi/0x1d2df280",
    "avg_score": "1.00"
  },
  {
    "author": "@dhudhu",
    "author_url": "https://farcaster.xyz/dhudhu",
    "casts": 1,
    "posts": 1,
    "comments": 0,
    "likes": 0,
    "recasts": 0,
    "replies": 1,
    "best_score": "1.00",
    "top_cast_url": "https://farcaster.xyz/dhudhu/0x55c97f1e",
    "avg_score": "1.00"
  },
  {
    "author": "@gaspardguerre",
    "author_url": "https://farcaster.xyz/gaspardguerre",
    "casts": 1,
    "posts": 1,
    "comments": 0,
    "likes": 0,
    "recasts": 0,
    "replies": 1,
    "best_score": "1.00",
    "top_cast_url": "https://farcaster.xyz/gaspardguerre/0xcfd89635",
    "avg_score": "1.00"
  },
  {
    "author": "@rosekeyes",
    "author_url": "https://farcaster.xyz/rosekeyes",
    "casts": 1,
    "posts": 0,
    "comments": 1,
    "likes": 0,
    "recasts": 0,
    "replies": 1,
    "best_score": "1.00",
    "top_cast_url": "https://farcaster.xyz/rosekeyes/0xc0bde320",
    "avg_score": "1.00"
  },
  {
    "author": "@shaka31",
    "author_url": "https://farcaster.xyz/shaka31",
    "casts": 1,
    "posts": 0,
    "comments": 1,
    "likes": 0,
    "recasts": 0,
    "replies": 1,
    "best_score": "1.00",
    "top_cast_url": "https://farcaster.xyz/shaka31/0x165dfea9",
    "avg_score": "1.00"
  },
  {
    "author": "@kalinda3331",
    "author_url": "https://farcaster.xyz/kalinda3331",
    "casts": 1,
    "posts": 0,
    "comments": 1,
    "likes": 0,
    "recasts": 0,
    "replies": 1,
    "best_score": "1.00",
    "top_cast_url": "https://farcaster.xyz/kalinda3331/0x11ca72f8",
    "avg_score": "1.00"
  }
]
