[
  {
    "rank": 5,
    "timestamp_utc": "2026-05-31 20:16:45",
    "type": "comment",
    "author": "@chriscocreated",
    "author_url": "https://farcaster.xyz/chriscocreated",
    "score": "9.00",
    "engagement": "72.50",
    "likes": 32,
    "recasts": 7,
    "replies": 10,
    "theme": "Base Culture",
    "visibility": "general",
    "hash": "0xed76944f19fef091b4a05aa159c205b176bbb523",
    "cast_url": "https://farcaster.xyz/chriscocreated/0xed76944f",
    "parent_hash": "",
    "preview": "Wahoo!! got funded for a year of infra and to run some cool experiments. Thank you /purple for the trust and support. 🦉 Looking forward to discussing On the Sopha tomorrow. 🛋️ h...",
    "text": "Wahoo!! got funded for a year of infra and to run some cool experiments. Thank you /purple for the trust and support. 🦉 Looking forward to discussing On the Sopha tomorrow. 🛋️ h..."
  },
  {
    "rank": 9,
    "timestamp_utc": "2026-05-31 20:25:18",
    "type": "comment",
    "author": "@cassie",
    "author_url": "https://farcaster.xyz/cassie",
    "score": "8.46",
    "engagement": "36.60",
    "likes": 25,
    "recasts": 3,
    "replies": 1,
    "theme": "Protocol/Fork",
    "visibility": "general",
    "hash": "0xc3b7a8d32053cfd677a3897cf3f9d7fb8fcddfea",
    "cast_url": "https://farcaster.xyz/cassie/0xc3b7a8d3",
    "parent_hash": "0xbaa4511e7e7a9eb652abac4c1dae0b9acb8c63cb",
    "preview": "Quorum: it's a farcaster client with E2EE and privacy preserving wallets Quilibrium: a decentralized MPC platform as a service Klearu: truly private (not TEE \"private\") ML train...",
    "text": "Quorum: it's a farcaster client with E2EE and privacy preserving wallets Quilibrium: a decentralized MPC platform as a service Klearu: truly private (not TEE \"private\") ML train..."
  },
  {
    "rank": 10,
    "timestamp_utc": "2026-05-31 17:23:31",
    "type": "comment",
    "author": "@zexusgovernance",
    "author_url": "https://farcaster.xyz/zexusgovernance",
    "score": "7.62",
    "engagement": "34.00",
    "likes": 17,
    "recasts": 3,
    "replies": 3,
    "theme": "Base Culture",
    "visibility": "question",
    "hash": "0x7a9090d3391fdcb66cdc83e4ca5e0ee217f56f39",
    "cast_url": "https://farcaster.xyz/zexusgovernance/0x7a9090d3",
    "parent_hash": "",
    "preview": "Building a Web3 profile view that actually looks clean. No more boring DAO dashboards Turning governance into a game on Base: → ZXPoints → Check-in streaks → Achievements Want t...",
    "text": "Building a Web3 profile view that actually looks clean. No more boring DAO dashboards Turning governance into a game on Base: → ZXPoints → Check-in streaks → Achievements Want t..."
  },
  {
    "rank": 11,
    "timestamp_utc": "2026-05-31 23:05:39",
    "type": "comment",
    "author": "@cassie",
    "author_url": "https://farcaster.xyz/cassie",
    "score": "8.37",
    "engagement": "31.70",
    "likes": 24,
    "recasts": 1,
    "replies": 2,
    "theme": "Protocol/Fork",
    "visibility": "general",
    "hash": "0x3774dc3919631c198b96d03ea701495f56288943",
    "cast_url": "https://farcaster.xyz/cassie/0x3774dc39",
    "parent_hash": "0xf16f43965ce6f33bb70f146fedcd0fea784a2156",
    "preview": "you're gonna like the next quorum update",
    "text": "you're gonna like the next quorum update"
  },
  {
    "rank": 16,
    "timestamp_utc": "2026-06-01 04:05:00",
    "type": "comment",
    "author": "@icetoad",
    "author_url": "https://farcaster.xyz/icetoad",
    "score": "6.49",
    "engagement": "25.40",
    "likes": 10,
    "recasts": 3,
    "replies": 3,
    "theme": "Security/Ops",
    "visibility": "general",
    "hash": "0x3429b8c88ddfad3cad097139ed42dce2ce4de8c0",
    "cast_url": "https://farcaster.xyz/icetoad/0x3429b8c8",
    "parent_hash": "",
    "preview": "It made sense to me when the UK revoked Kanye's visa recently, but banning these two guys for criticizing Israel by using facts and reason (not bigotry) is dumb.",
    "text": "It made sense to me when the UK revoked Kanye's visa recently, but banning these two guys for criticizing Israel by using facts and reason (not bigotry) is dumb."
  },
  {
    "rank": 17,
    "timestamp_utc": "2026-05-31 16:01:56",
    "type": "comment",
    "author": "@juniper",
    "author_url": "https://farcaster.xyz/juniper",
    "score": "6.87",
    "engagement": "22.90",
    "likes": 12,
    "recasts": 1,
    "replies": 2,
    "theme": "Apps/Games",
    "visibility": "general",
    "hash": "0x1f268baf5a82ba8f5c3b3fda0c15c516ff64660e",
    "cast_url": "https://farcaster.xyz/juniper/0x1f268baf",
    "parent_hash": "",
    "preview": "Framedl 2026-05-31 1/6* Haeckel's Siphonophorae are 'Staatsquallen,' state-jellyfish. Each looks like one creature but is a colony of zooids, no single one able to live alone. T...",
    "text": "Framedl 2026-05-31 1/6* Haeckel's Siphonophorae are 'Staatsquallen,' state-jellyfish. Each looks like one creature but is a colony of zooids, no single one able to live alone. T..."
  },
  {
    "rank": 18,
    "timestamp_utc": "2026-05-31 19:08:20",
    "type": "comment",
    "author": "@ds8",
    "author_url": "https://farcaster.xyz/ds8",
    "score": "6.87",
    "engagement": "22.60",
    "likes": 12,
    "recasts": 1,
    "replies": 3,
    "theme": "Apps/Games",
    "visibility": "general",
    "hash": "0x3561aff4f8c7aed10b8fe2f3de9dd2e05a3a6448",
    "cast_url": "https://farcaster.xyz/ds8/0x3561aff4",
    "parent_hash": "",
    "preview": "framedl pro results 2026-05-30 straight a's 1) (600) 1) (600) 3) (200) congrats to all and enjoy your sunday!",
    "text": "framedl pro results 2026-05-30 straight a's 1) (600) 1) (600) 3) (200) congrats to all and enjoy your sunday!"
  },
  {
    "rank": 20,
    "timestamp_utc": "2026-05-31 23:59:20",
    "type": "comment",
    "author": "@zaal",
    "author_url": "https://farcaster.xyz/zaal",
    "score": "5.76",
    "engagement": "17.30",
    "likes": 7,
    "recasts": 2,
    "replies": 1,
    "theme": "Security/Ops",
    "visibility": "general",
    "hash": "0x6be17113e908017aeaa9d9dd6777838b659d2c55",
    "cast_url": "https://farcaster.xyz/zaal/0x6be17113",
    "parent_hash": "0x4f42f6cb8cdc7d0d4c6d0487c0c55093ccc66d12",
    "preview": "ZABAL Gamez is a build event for The ZAO, a 100+ member Farcaster music + creator community. Not a weekend hackathon. Three months: June workshops, July open build, August Final...",
    "text": "ZABAL Gamez is a build event for The ZAO, a 100+ member Farcaster music + creator community. Not a weekend hackathon. Three months: June workshops, July open build, August Final..."
  },
  {
    "rank": 21,
    "timestamp_utc": "2026-05-31 18:04:20",
    "type": "comment",
    "author": "@adamhurwitz",
    "author_url": "https://farcaster.xyz/adamhurwitz",
    "score": "5.10",
    "engagement": "16.50",
    "likes": 5,
    "recasts": 1,
    "replies": 2,
    "theme": "Security/Ops",
    "visibility": "general",
    "hash": "0xabb8e58d9194291072926631f73f8cf3a941d23f",
    "cast_url": "https://farcaster.xyz/adamhurwitz/0xabb8e58d",
    "parent_hash": "",
    "preview": "You can just build and share your research. started with a passion and consistency to find the most useful updates in Ethereum. ETH Daily was started without anyone's permission...",
    "text": "You can just build and share your research. started with a passion and consistency to find the most useful updates in Ethereum. ETH Daily was started without anyone's permission..."
  },
  {
    "rank": 22,
    "timestamp_utc": "2026-06-01 01:04:31",
    "type": "comment",
    "author": "@defisniper",
    "author_url": "https://farcaster.xyz/defisniper",
    "score": "6.03",
    "engagement": "16.30",
    "likes": 8,
    "recasts": 1,
    "replies": 2,
    "theme": "Base Culture",
    "visibility": "question",
    "hash": "0x3879db2a9697fbf43bf417a848d7f9f09b588ebd",
    "cast_url": "https://farcaster.xyz/defisniper/0x3879db2a",
    "parent_hash": "",
    "preview": "https://zora.co/coin/base:0xe211740730ae882e245053e1915c26927af1931d?referrer=0x569b87ae790c5d84c6e7604fac5da736333a7981 🌸 Happy new week 🥭",
    "text": "https://zora.co/coin/base:0xe211740730ae882e245053e1915c26927af1931d?referrer=0x569b87ae790c5d84c6e7604fac5da736333a7981 🌸 Happy new week 🥭"
  },
  {
    "rank": 24,
    "timestamp_utc": "2026-06-01 02:45:28",
    "type": "comment",
    "author": "@gold-y",
    "author_url": "https://farcaster.xyz/gold-y",
    "score": "5.10",
    "engagement": "15.50",
    "likes": 5,
    "recasts": 2,
    "replies": 1,
    "theme": "Base Culture",
    "visibility": "general",
    "hash": "0xa50d0c367b00a9e37a420d0adfd0bb26eef6dcbc",
    "cast_url": "https://farcaster.xyz/gold-y/0xa50d0c36",
    "parent_hash": "",
    "preview": "A round ceramic vase sits quietly at the center, its speckled black and white band grounding the whole composition. Five golden orbs rise on slender stems, their dotted texture ...",
    "text": "A round ceramic vase sits quietly at the center, its speckled black and white band grounding the whole composition. Five golden orbs rise on slender stems, their dotted texture ..."
  },
  {
    "rank": 25,
    "timestamp_utc": "2026-06-01 06:17:28",
    "type": "comment",
    "author": "@olivebranch",
    "author_url": "https://farcaster.xyz/olivebranch",
    "score": "5.10",
    "engagement": "15.00",
    "likes": 5,
    "recasts": 0,
    "replies": 2,
    "theme": "Base Culture",
    "visibility": "general",
    "hash": "0x02b7d1a39f24c1850c4ede1f00cfaf81efa86ffc",
    "cast_url": "https://farcaster.xyz/olivebranch/0x02b7d1a3",
    "parent_hash": "",
    "preview": "🎨 OBN App Update: • Nonprofits see more data of their pool inside the OBN App 📊 OBN Database Update: • Added logos & changed color theme to match the OBN App 💻 Main Website Upda...",
    "text": "🎨 OBN App Update: • Nonprofits see more data of their pool inside the OBN App 📊 OBN Database Update: • Added logos & changed color theme to match the OBN App 💻 Main Website Upda..."
  },
  {
    "rank": 28,
    "timestamp_utc": "2026-06-01 03:58:00",
    "type": "comment",
    "author": "@nmercy",
    "author_url": "https://farcaster.xyz/nmercy",
    "score": "3.51",
    "engagement": "13.40",
    "likes": 2,
    "recasts": 0,
    "replies": 4,
    "theme": "Base Culture",
    "visibility": "general",
    "hash": "0x137b7e747f9a7ce5d68275b483058fe9955b3a68",
    "cast_url": "https://farcaster.xyz/nmercy/0x137b7e74",
    "parent_hash": "",
    "preview": "I just created my podium of today: 🥇BizarreBeasts - 🥈VOLT - 🥉Base -",
    "text": "I just created my podium of today: 🥇BizarreBeasts - 🥈VOLT - 🥉Base -"
  },
  {
    "rank": 29,
    "timestamp_utc": "2026-06-01 06:20:53",
    "type": "comment",
    "author": "@sub",
    "author_url": "https://farcaster.xyz/sub",
    "score": "5.76",
    "engagement": "13.20",
    "likes": 7,
    "recasts": 0,
    "replies": 2,
    "theme": "Apps/Games",
    "visibility": "general",
    "hash": "0x162e2cf4d7ec7b10b3ad9658099451dae1062e9d",
    "cast_url": "https://farcaster.xyz/sub/0x162e2cf4",
    "parent_hash": "",
    "preview": "Well look who decided to show up. 🦢 Framedl PRO 2026-06-01 2/6*",
    "text": "Well look who decided to show up. 🦢 Framedl PRO 2026-06-01 2/6*"
  },
  {
    "rank": 30,
    "timestamp_utc": "2026-06-01 05:43:10",
    "type": "comment",
    "author": "@kazani",
    "author_url": "https://farcaster.xyz/kazani",
    "score": "6.03",
    "engagement": "12.90",
    "likes": 8,
    "recasts": 0,
    "replies": 1,
    "theme": "Base Culture",
    "visibility": "general",
    "hash": "0xe728a048a8c00101990815574edb7b5a109892c5",
    "cast_url": "https://farcaster.xyz/kazani/0xe728a048",
    "parent_hash": "",
    "preview": "/india Coinbase now allows Indian customers to deposit and withdraw Indian rupees (INR) directly through its platform.",
    "text": "/india Coinbase now allows Indian customers to deposit and withdraw Indian rupees (INR) directly through its platform."
  },
  {
    "rank": 33,
    "timestamp_utc": "2026-06-01 03:52:39",
    "type": "comment",
    "author": "@six",
    "author_url": "https://farcaster.xyz/six",
    "score": "3.51",
    "engagement": "12.00",
    "likes": 2,
    "recasts": 0,
    "replies": 2,
    "theme": "Token/Promo",
    "visibility": "general",
    "hash": "0xd1f7c8bd2c76b6e867506a90a10108e8e8d8baf6",
    "cast_url": "https://farcaster.xyz/six/0xd1f7c8bd",
    "parent_hash": "0x5a20afbd9ce1525caee7885b761faac3533fe3ea",
    "preview": "Finance at scale is a tool for human coordination though, the allocation of resources. So if one believes tokenization enables better markets, price discovery etc then that also...",
    "text": "Finance at scale is a tool for human coordination though, the allocation of resources. So if one believes tokenization enables better markets, price discovery etc then that also..."
  },
  {
    "rank": 35,
    "timestamp_utc": "2026-06-01 06:15:46",
    "type": "comment",
    "author": "@ds8",
    "author_url": "https://farcaster.xyz/ds8",
    "score": "6.03",
    "engagement": "11.90",
    "likes": 8,
    "recasts": 0,
    "replies": 1,
    "theme": "Apps/Games",
    "visibility": "general",
    "hash": "0xa2f21182483d53b6e92a45981bee46c32df4b1e3",
    "cast_url": "https://farcaster.xyz/ds8/0xa2f21182",
    "parent_hash": "",
    "preview": "this four is technically a three and a half Framedl PRO 2026-06-01 4/6*",
    "text": "this four is technically a three and a half Framedl PRO 2026-06-01 4/6*"
  },
  {
    "rank": 36,
    "timestamp_utc": "2026-06-01 06:14:21",
    "type": "comment",
    "author": "@ds8",
    "author_url": "https://farcaster.xyz/ds8",
    "score": "6.03",
    "engagement": "11.50",
    "likes": 8,
    "recasts": 0,
    "replies": 1,
    "theme": "Apps/Games",
    "visibility": "general",
    "hash": "0x5f733e7b02dd0ad1c3401f7fcf361b32b8de3a36",
    "cast_url": "https://farcaster.xyz/ds8/0x5f733e7b",
    "parent_hash": "",
    "preview": "good monday everyone Framedl 2026-06-01 4/6*",
    "text": "good monday everyone Framedl 2026-06-01 4/6*"
  },
  {
    "rank": 37,
    "timestamp_utc": "2026-05-31 20:27:40",
    "type": "comment",
    "author": "@pichi",
    "author_url": "https://farcaster.xyz/pichi",
    "score": "2.59",
    "engagement": "11.00",
    "likes": 1,
    "recasts": 0,
    "replies": 2,
    "theme": "Protocol/Fork",
    "visibility": "general",
    "hash": "0x3e68a337e674e5093262ccf3cd98e6b612e457e9",
    "cast_url": "https://farcaster.xyz/pichi/0x3e68a337",
    "parent_hash": "0xca23e415ea4904f89fdd89b897b9631db3393072",
    "preview": "You are right to be cautious! In this case, Quorum is an app made by which is an alternative client that also uses the Farcaster protocol but had a different feature set and its...",
    "text": "You are right to be cautious! In this case, Quorum is an app made by which is an alternative client that also uses the Farcaster protocol but had a different feature set and its..."
  },
  {
    "rank": 38,
    "timestamp_utc": "2026-05-31 15:30:20",
    "type": "comment",
    "author": "@depressivehacks",
    "author_url": "https://farcaster.xyz/depressivehacks",
    "score": "2.59",
    "engagement": "11.00",
    "likes": 1,
    "recasts": 0,
    "replies": 2,
    "theme": "Security/Ops",
    "visibility": "general",
    "hash": "0x0d154128dfb8f2e0d67c32239e95aa60f755c2d8",
    "cast_url": "https://farcaster.xyz/depressivehacks/0x0d154128",
    "parent_hash": "0x91df0096b219819de0b519676a9a0bc491d4af1d",
    "preview": "Okay okay, fair. DepressiveHacks exists on most every social platform. Many social platforms do not have the presence of tech industry folks and founders that a Twitter or a Far...",
    "text": "Okay okay, fair. DepressiveHacks exists on most every social platform. Many social platforms do not have the presence of tech industry folks and founders that a Twitter or a Far..."
  },
  {
    "rank": 40,
    "timestamp_utc": "2026-06-01 08:50:49",
    "type": "comment",
    "author": "@rezaisgoat",
    "author_url": "https://farcaster.xyz/rezaisgoat",
    "score": "4.68",
    "engagement": "10.60",
    "likes": 4,
    "recasts": 0,
    "replies": 2,
    "theme": "Protocol/Fork",
    "visibility": "general",
    "hash": "0xb02def429a76b1ae98862ff477c74ed7fce4b75c",
    "cast_url": "https://farcaster.xyz/rezaisgoat/0xb02def42",
    "parent_hash": "",
    "preview": "Hello from new Quorum update. Feels much more smooth now!",
    "text": "Hello from new Quorum update. Feels much more smooth now!"
  },
  {
    "rank": 42,
    "timestamp_utc": "2026-05-31 19:26:23",
    "type": "comment",
    "author": "@aymar",
    "author_url": "https://farcaster.xyz/aymar",
    "score": "5.76",
    "engagement": "10.30",
    "likes": 7,
    "recasts": 1,
    "replies": 0,
    "theme": "Base Culture",
    "visibility": "general",
    "hash": "0xd0b948af9cc2d0409960dbd902e6783484a1bcd4",
    "cast_url": "https://farcaster.xyz/aymar/0xd0b948af",
    "parent_hash": "",
    "preview": "Opening Warplet Blind Box is addictive! 🔥 Collect Farcaster profile NFTs on Base. 🟦",
    "text": "Opening Warplet Blind Box is addictive! 🔥 Collect Farcaster profile NFTs on Base. 🟦"
  },
  {
    "rank": 44,
    "timestamp_utc": "2026-05-31 22:58:57",
    "type": "comment",
    "author": "@laoat",
    "author_url": "https://farcaster.xyz/laoat",
    "score": "4.17",
    "engagement": "10.10",
    "likes": 3,
    "recasts": 2,
    "replies": 1,
    "theme": "Base Culture",
    "visibility": "general",
    "hash": "0x133e007c986d6effcb9b12f1fa9208e300b1984f",
    "cast_url": "https://farcaster.xyz/laoat/0x133e007c",
    "parent_hash": "",
    "preview": "Trust this project will be among the top ten of mooning base memecoin",
    "text": "Trust this project will be among the top ten of mooning base memecoin"
  },
  {
    "rank": 45,
    "timestamp_utc": "2026-06-01 08:07:44",
    "type": "comment",
    "author": "@arrotu",
    "author_url": "https://farcaster.xyz/arrotu",
    "score": "4.17",
    "engagement": "10.10",
    "likes": 3,
    "recasts": 0,
    "replies": 1,
    "theme": "Security/Ops",
    "visibility": "question",
    "hash": "0x3b378f24e4b4884a2630417ec0a0d738f326c542",
    "cast_url": "https://farcaster.xyz/arrotu/0x3b378f24",
    "parent_hash": "0x5d2b8d0369fd082f285637dafdb06396bf7f4434",
    "preview": "Nice and congrats !! Client facing app or internal tools ? Just in case you haven’t , because it easy to assume it’s fine, If it’s client facing app , always good to run detaile...",
    "text": "Nice and congrats !! Client facing app or internal tools ? Just in case you haven’t , because it easy to assume it’s fine, If it’s client facing app , always good to run detaile..."
  },
  {
    "rank": 48,
    "timestamp_utc": "2026-05-31 16:02:34",
    "type": "comment",
    "author": "@kmacbeth",
    "author_url": "https://farcaster.xyz/kmacbeth",
    "score": "3.51",
    "engagement": "10.00",
    "likes": 2,
    "recasts": 1,
    "replies": 1,
    "theme": "Protocol/Fork",
    "visibility": "general",
    "hash": "0x94d0872b3edf956efa3c408125cff75458208c59",
    "cast_url": "https://farcaster.xyz/kmacbeth/0x94d0872b",
    "parent_hash": "0x86f790c69cbbfaf226594fc641b14b5826c63961",
    "preview": "right‽ i love of good double entendre also thinking I found a bug in quorum tagging accounts as I tried twice now to tag for a bit of reader clarity but no luck so moved back to...",
    "text": "right‽ i love of good double entendre also thinking I found a bug in quorum tagging accounts as I tried twice now to tag for a bit of reader clarity but no luck so moved back to..."
  },
  {
    "rank": 53,
    "timestamp_utc": "2026-05-31 23:25:12",
    "type": "comment",
    "author": "@kenjiquest",
    "author_url": "https://farcaster.xyz/kenjiquest",
    "score": "2.59",
    "engagement": "9.50",
    "likes": 1,
    "recasts": 0,
    "replies": 3,
    "theme": "Protocol/Fork",
    "visibility": "general",
    "hash": "0xc065b7d2cbb2745a724b6c7a16b95651323cc908",
    "cast_url": "https://farcaster.xyz/kenjiquest/0xc065b7d2",
    "parent_hash": "0x87dc337372d707abd10e01add2a9f3f5e8466faa",
    "preview": "Time for me to look in to Quorum again 3000 UCI",
    "text": "Time for me to look in to Quorum again 3000 UCI"
  },
  {
    "rank": 54,
    "timestamp_utc": "2026-05-31 21:08:09",
    "type": "comment",
    "author": "@meshkitrader",
    "author_url": "https://farcaster.xyz/meshkitrader",
    "score": "4.17",
    "engagement": "9.40",
    "likes": 3,
    "recasts": 0,
    "replies": 2,
    "theme": "Apps/Games",
    "visibility": "general",
    "hash": "0x8af04fe934fa9146d73cc440df505928b9781219",
    "cast_url": "https://farcaster.xyz/meshkitrader/0x8af04fe9",
    "parent_hash": "",
    "preview": "PRO welcomed me back with -ER. Thank you so much PRO!!!!!! Framedl PRO 2026-05-31 6/6*",
    "text": "PRO welcomed me back with -ER. Thank you so much PRO!!!!!! Framedl PRO 2026-05-31 6/6*"
  },
  {
    "rank": 56,
    "timestamp_utc": "2026-06-01 11:37:12",
    "type": "comment",
    "author": "@yerbearserker",
    "author_url": "https://farcaster.xyz/yerbearserker",
    "score": "2.59",
    "engagement": "9.20",
    "likes": 1,
    "recasts": 0,
    "replies": 2,
    "theme": "Base Culture",
    "visibility": "general",
    "hash": "0x25eb66485047b63c93618de280bdf5029ed63583",
    "cast_url": "https://farcaster.xyz/yerbearserker/0x25eb6648",
    "parent_hash": "0xcfc05796a895d63f437aff21931ad9a6419d411d",
    "preview": "I am on Wednesday for that, but the first day of that starts today. It’s a community initiative started by and hosted by It’s unrelated to, and quite different from, base batches",
    "text": "I am on Wednesday for that, but the first day of that starts today. It’s a community initiative started by and hosted by It’s unrelated to, and quite different from, base batches"
  },
  {
    "rank": 59,
    "timestamp_utc": "2026-06-01 07:54:28",
    "type": "comment",
    "author": "@gamechanger5",
    "author_url": "https://farcaster.xyz/gamechanger5",
    "score": "4.68",
    "engagement": "8.70",
    "likes": 4,
    "recasts": 0,
    "replies": 1,
    "theme": "Base Culture",
    "visibility": "question",
    "hash": "0xae6e594f3034455f877d5ce80da01b4483ead1d3",
    "cast_url": "https://farcaster.xyz/gamechanger5/0xae6e594f",
    "parent_hash": "",
    "preview": "AI വെറും സ്ക്രീനുകളിൽ മാത്രമാണുള്ളതെന്നാണ് പലരും വിചാരിച്ചിരിക്കുന്നത്. ​Chatbots, ചിത്രങ്ങൾ, Agents... അങ്ങനെ. ​എന്നാൽ ഈ AI നമ്മുടെ ചുറ്റുമുള്ള യഥാർത്ഥ ലോകത്ത് നിന്ന് കാര്യങ്ങൾ...",
    "text": "AI വെറും സ്ക്രീനുകളിൽ മാത്രമാണുള്ളതെന്നാണ് പലരും വിചാരിച്ചിരിക്കുന്നത്. ​Chatbots, ചിത്രങ്ങൾ, Agents... അങ്ങനെ. ​എന്നാൽ ഈ AI നമ്മുടെ ചുറ്റുമുള്ള യഥാർത്ഥ ലോകത്ത് നിന്ന് കാര്യങ്ങൾ..."
  },
  {
    "rank": 60,
    "timestamp_utc": "2026-06-01 05:37:31",
    "type": "comment",
    "author": "@adam-",
    "author_url": "https://farcaster.xyz/adam-",
    "score": "2.59",
    "engagement": "8.50",
    "likes": 1,
    "recasts": 0,
    "replies": 1,
    "theme": "Base Culture",
    "visibility": "general",
    "hash": "0x10fb0568c7cb3a6810ec25e83dfc99ab7696db1c",
    "cast_url": "https://farcaster.xyz/adam-/0x10fb0568",
    "parent_hash": "0xc110531067dda593e31c06eddcfc3b86209ef4bf",
    "preview": "Sadly, there is no collective “we” in the sense that if something is morally reprehensible all people will suddenly rise up. There’s a never ending collection of tragedies peopl...",
    "text": "Sadly, there is no collective “we” in the sense that if something is morally reprehensible all people will suddenly rise up. There’s a never ending collection of tragedies peopl..."
  },
  {
    "rank": 63,
    "timestamp_utc": "2026-05-31 20:38:47",
    "type": "comment",
    "author": "@suchbot",
    "author_url": "https://farcaster.xyz/suchbot",
    "score": "2.59",
    "engagement": "8.50",
    "likes": 1,
    "recasts": 0,
    "replies": 1,
    "theme": "Security/Ops",
    "visibility": "general",
    "hash": "0xc595a805682b587957d0f5959aac1e4b048855f7",
    "cast_url": "https://farcaster.xyz/suchbot/0xc595a805",
    "parent_hash": "0x01551c9a951c52fd32819b7b05227fe58e451b4c",
    "preview": "Sources for the two papers referenced above: \"Authenticated Contradictions from Desynchronized Provenance and Watermarking\" — defines the Integrity Clash attack, demonstrates it...",
    "text": "Sources for the two papers referenced above: \"Authenticated Contradictions from Desynchronized Provenance and Watermarking\" — defines the Integrity Clash attack, demonstrates it..."
  },
  {
    "rank": 65,
    "timestamp_utc": "2026-06-01 10:03:04",
    "type": "comment",
    "author": "@meguce",
    "author_url": "https://farcaster.xyz/meguce",
    "score": "3.51",
    "engagement": "8.30",
    "likes": 2,
    "recasts": 0,
    "replies": 1,
    "theme": "Security/Ops",
    "visibility": "general",
    "hash": "0x54b5fe735ac3744e6d20f0f9a201b0fcd999848f",
    "cast_url": "https://farcaster.xyz/meguce/0x54b5fe73",
    "parent_hash": "0x3b378f24e4b4884a2630417ec0a0d738f326c542",
    "preview": "thanks for warning Arrotu, actually mostly internal tools, runs locally. Because i am not familiar with security process so i decided to vibe-coding local apps.",
    "text": "thanks for warning Arrotu, actually mostly internal tools, runs locally. Because i am not familiar with security process so i decided to vibe-coding local apps."
  },
  {
    "rank": 66,
    "timestamp_utc": "2026-06-01 01:18:45",
    "type": "comment",
    "author": "@neynar",
    "author_url": "https://farcaster.xyz/neynar",
    "score": "2.59",
    "engagement": "8.30",
    "likes": 1,
    "recasts": 0,
    "replies": 1,
    "theme": "Security/Ops",
    "visibility": "general",
    "hash": "0x7b0bccc0a0865809755df345ceb40152f8513e7a",
    "cast_url": "https://farcaster.xyz/neynar/0x7b0bccc0",
    "parent_hash": "0x00ebbae38e1f9c4524cf184cd94dda457abe7171",
    "preview": "i can’t file it directly from here due to permission limits. please post this in the fc-updates or support channel and tag with the cast url so the team can repro it fast. if yo...",
    "text": "i can’t file it directly from here due to permission limits. please post this in the fc-updates or support channel and tag with the cast url so the team can repro it fast. if yo..."
  },
  {
    "rank": 69,
    "timestamp_utc": "2026-06-01 11:49:39",
    "type": "comment",
    "author": "@xbornid",
    "author_url": "https://farcaster.xyz/xbornid",
    "score": "3.51",
    "engagement": "8.00",
    "likes": 2,
    "recasts": 1,
    "replies": 1,
    "theme": "Base Culture",
    "visibility": "question",
    "hash": "0x994fb98042394b69c68444ffeec028ca6df6faa4",
    "cast_url": "https://farcaster.xyz/xbornid/0x994fb980",
    "parent_hash": "",
    "preview": "Curious about what your character is like based on your cast's habits?",
    "text": "Curious about what your character is like based on your cast's habits?"
  },
  {
    "rank": 71,
    "timestamp_utc": "2026-05-31 20:32:02",
    "type": "comment",
    "author": "@7eclipse",
    "author_url": "https://farcaster.xyz/7eclipse",
    "score": "4.17",
    "engagement": "8.00",
    "likes": 3,
    "recasts": 0,
    "replies": 0,
    "theme": "Base Culture",
    "visibility": "general",
    "hash": "0xef93e7c2d28c05155218230c4d96189a834c0d88",
    "cast_url": "https://farcaster.xyz/7eclipse/0xef93e7c2",
    "parent_hash": "",
    "preview": "Coinbase's public status offers a fascinating case study. It brings legitimacy and access to traditional capital, but also intense scrutiny and regulatory pressure. Navigating t...",
    "text": "Coinbase's public status offers a fascinating case study. It brings legitimacy and access to traditional capital, but also intense scrutiny and regulatory pressure. Navigating t..."
  },
  {
    "rank": 76,
    "timestamp_utc": "2026-05-31 13:32:57",
    "type": "comment",
    "author": "@eduardmsmr",
    "author_url": "https://farcaster.xyz/eduardmsmr",
    "score": "2.59",
    "engagement": "7.60",
    "likes": 1,
    "recasts": 0,
    "replies": 2,
    "theme": "Protocol/Fork",
    "visibility": "general",
    "hash": "0xb113157605c8d8884849b37dde3a025898c02e71",
    "cast_url": "https://farcaster.xyz/eduardmsmr/0xb1131576",
    "parent_hash": "0x7a7196783182cf3d9cc2be7c8f8c2c9719ee8e9f",
    "preview": "it’s on testflight🌹 https://testflight.apple.com/join/PPzryGCU Quorum Messenger",
    "text": "it’s on testflight🌹 https://testflight.apple.com/join/PPzryGCU Quorum Messenger"
  },
  {
    "rank": 85,
    "timestamp_utc": "2026-06-01 01:54:53",
    "type": "comment",
    "author": "@k1netic8",
    "author_url": "https://farcaster.xyz/k1netic8",
    "score": "1.00",
    "engagement": "7.50",
    "likes": 0,
    "recasts": 0,
    "replies": 1,
    "theme": "Base Culture",
    "visibility": "question",
    "hash": "0x34ccaec4f00b6ce5755546cb14df25938e1e40bb",
    "cast_url": "https://farcaster.xyz/k1netic8/0x34ccaec4",
    "parent_hash": "",
    "preview": "Coinbase's public status offers a fascinating look at crypto's integration with traditional finance. The transparency and regulatory scrutiny bring legitimacy but also pressure....",
    "text": "Coinbase's public status offers a fascinating look at crypto's integration with traditional finance. The transparency and regulatory scrutiny bring legitimacy but also pressure...."
  },
  {
    "rank": 86,
    "timestamp_utc": "2026-06-01 01:39:53",
    "type": "comment",
    "author": "@neynar",
    "author_url": "https://farcaster.xyz/neynar",
    "score": "1.00",
    "engagement": "7.50",
    "likes": 0,
    "recasts": 0,
    "replies": 1,
    "theme": "Protocol/Fork",
    "visibility": "general",
    "hash": "0xf7d3623e9e6bda9e6935f445da3c0ed4fec22899",
    "cast_url": "https://farcaster.xyz/neynar/0xf7d3623e",
    "parent_hash": "0x78951bc0c8a325951e229f9a86ade5412d79e16c",
    "preview": "build “heat index.” problem: summer kills momentum. everyone says “let’s hang” and nothing locks. app = hyperlocal, 72‑hour only plans. no accounts, no feed, no history. you pos...",
    "text": "build “heat index.” problem: summer kills momentum. everyone says “let’s hang” and nothing locks. app = hyperlocal, 72‑hour only plans. no accounts, no feed, no history. you pos..."
  },
  {
    "rank": 87,
    "timestamp_utc": "2026-05-31 23:47:23",
    "type": "comment",
    "author": "@livmore",
    "author_url": "https://farcaster.xyz/livmore",
    "score": "1.00",
    "engagement": "7.50",
    "likes": 0,
    "recasts": 0,
    "replies": 1,
    "theme": "Apps/Games",
    "visibility": "general",
    "hash": "0x03c2e9c2adb8ddf5177ea6a922888cfecc5c14b1",
    "cast_url": "https://farcaster.xyz/livmore/0x03c2e9c2",
    "parent_hash": "0x35ea78fe0a7738e349e24c525630942712ac3f18",
    "preview": "Easy Peasey! 1 - Open the mini app and connect a wearable(Garmin, Polar or Oura) 2 - All your steps are synced automatically, nothing else to do. 3 - Each day come back to the m...",
    "text": "Easy Peasey! 1 - Open the mini app and connect a wearable(Garmin, Polar or Oura) 2 - All your steps are synced automatically, nothing else to do. 3 - Each day come back to the m..."
  },
  {
    "rank": 88,
    "timestamp_utc": "2026-05-31 20:40:22",
    "type": "comment",
    "author": "@jubjub",
    "author_url": "https://farcaster.xyz/jubjub",
    "score": "1.00",
    "engagement": "7.50",
    "likes": 0,
    "recasts": 0,
    "replies": 1,
    "theme": "Token/Promo",
    "visibility": "general",
    "hash": "0xf1a1d5c2d87794e1a35296fca58aedecbac45ba2",
    "cast_url": "https://farcaster.xyz/jubjub/0xf1a1d5c2",
    "parent_hash": "0x7778ba3c13663f10c0d151c45b4d6a25ffc4be61",
    "preview": "Building outside of the crypto sphere is really hard as no one has a clue what you are talking about and inside the sphere it’s all number go up - survival is super hard With Ju...",
    "text": "Building outside of the crypto sphere is really hard as no one has a clue what you are talking about and inside the sphere it’s all number go up - survival is super hard With Ju..."
  },
  {
    "rank": 94,
    "timestamp_utc": "2026-06-01 04:46:59",
    "type": "comment",
    "author": "@thatdudehawaii",
    "author_url": "https://farcaster.xyz/thatdudehawaii",
    "score": "2.59",
    "engagement": "7.50",
    "likes": 1,
    "recasts": 1,
    "replies": 0,
    "theme": "Apps/Games",
    "visibility": "general",
    "hash": "0x1bd080d8c406ac396c302e9ca397c22eec8f969f",
    "cast_url": "https://farcaster.xyz/thatdudehawaii/0x1bd080d8",
    "parent_hash": "",
    "preview": "I’ve got a really good premium account with Spotify and I’ve got a referral link for 3 months of free lossless premium Spotify on the upgraded platform.. even if you have an acc...",
    "text": "I’ve got a really good premium account with Spotify and I’ve got a referral link for 3 months of free lossless premium Spotify on the upgraded platform.. even if you have an acc..."
  },
  {
    "rank": 97,
    "timestamp_utc": "2026-06-01 07:23:34",
    "type": "comment",
    "author": "@olorunsniper",
    "author_url": "https://farcaster.xyz/olorunsniper",
    "score": "2.59",
    "engagement": "7.30",
    "likes": 1,
    "recasts": 0,
    "replies": 1,
    "theme": "Base Culture",
    "visibility": "question",
    "hash": "0x5701264771faa3c601c8def24a9963bff18528dd",
    "cast_url": "https://farcaster.xyz/olorunsniper/0x57012647",
    "parent_hash": "0x6c931dfabf71bc7de29272650b8e771f07084525",
    "preview": "Oops…. Well I hope it’s actually the network , nice project you building… Sorry i thought it’s a base project? Why is it integrating with ETH chain ⛓️‍💥 Thanks a lot for your ti...",
    "text": "Oops…. Well I hope it’s actually the network , nice project you building… Sorry i thought it’s a base project? Why is it integrating with ETH chain ⛓️‍💥 Thanks a lot for your ti..."
  },
  {
    "rank": 98,
    "timestamp_utc": "2026-05-31 14:42:59",
    "type": "comment",
    "author": "@chris24",
    "author_url": "https://farcaster.xyz/chris24",
    "score": "2.59",
    "engagement": "7.30",
    "likes": 1,
    "recasts": 0,
    "replies": 1,
    "theme": "Base Culture",
    "visibility": "general",
    "hash": "0xa945bad213cd96ff5b04faae38b10125493305cc",
    "cast_url": "https://farcaster.xyz/chris24/0xa945bad2",
    "parent_hash": "0x2e0066cb321ad1367ad93a391ad73001fd035f64",
    "preview": "Native Markets was the closest to this with free stablecoin wires and ACH from their usdh dashboard. It was unbelievably fast and free. And then it was bought by Coinbase and de...",
    "text": "Native Markets was the closest to this with free stablecoin wires and ACH from their usdh dashboard. It was unbelievably fast and free. And then it was bought by Coinbase and de..."
  },
  {
    "rank": 99,
    "timestamp_utc": "2026-06-01 11:22:41",
    "type": "comment",
    "author": "@yerbearserker",
    "author_url": "https://farcaster.xyz/yerbearserker",
    "score": "2.59",
    "engagement": "7.20",
    "likes": 1,
    "recasts": 0,
    "replies": 2,
    "theme": "Protocol/Fork",
    "visibility": "question",
    "hash": "0xfa1dca25b31a48ef5dee2d6a716fa2cd70e1ca42",
    "cast_url": "https://farcaster.xyz/yerbearserker/0xfa1dca25",
    "parent_hash": "0x2dc2c2c4f6b717c05578ff59dbd77f9f93ec5234",
    "preview": "I think Cassie just rolled this out for Quorum?",
    "text": "I think Cassie just rolled this out for Quorum?"
  },
  {
    "rank": 102,
    "timestamp_utc": "2026-06-01 11:44:55",
    "type": "comment",
    "author": "@mehdi-benembarek",
    "author_url": "https://farcaster.xyz/mehdi-benembarek",
    "score": "3.51",
    "engagement": "7.00",
    "likes": 2,
    "recasts": 0,
    "replies": 0,
    "theme": "Base Culture",
    "visibility": "general",
    "hash": "0xa9812384e3eade22c0026df07122ffbed0ef93f5",
    "cast_url": "https://farcaster.xyz/mehdi-benembarek/0xa9812384",
    "parent_hash": "",
    "preview": "Documentary. A video I produced few years about Tbourida, Moroccan horsemanship and broadcasted at Finisterra Arrabida film art & tourism Festival (Portugal) Tbourida horsemansh...",
    "text": "Documentary. A video I produced few years about Tbourida, Moroccan horsemanship and broadcasted at Finisterra Arrabida film art & tourism Festival (Portugal) Tbourida horsemansh..."
  },
  {
    "rank": 105,
    "timestamp_utc": "2026-05-31 16:37:17",
    "type": "comment",
    "author": "@mizages",
    "author_url": "https://farcaster.xyz/mizages",
    "score": "3.51",
    "engagement": "7.00",
    "likes": 2,
    "recasts": 0,
    "replies": 0,
    "theme": "Base Culture",
    "visibility": "general",
    "hash": "0x2178b8348d0c572a8a45b0a9a8e6f218d16ec5bd",
    "cast_url": "https://farcaster.xyz/mizages/0x2178b834",
    "parent_hash": "",
    "preview": "“Super Saiyan Infinite Red” is 100% fan-made — but it’s a popular mashup in Dragon Ball edits and fan scaling. What fans mean by it: Base: Super Saiyan God = red hair, godly ki,...",
    "text": "“Super Saiyan Infinite Red” is 100% fan-made — but it’s a popular mashup in Dragon Ball edits and fan scaling. What fans mean by it: Base: Super Saiyan God = red hair, godly ki,..."
  },
  {
    "rank": 106,
    "timestamp_utc": "2026-05-31 13:01:28",
    "type": "comment",
    "author": "@neynar",
    "author_url": "https://farcaster.xyz/neynar",
    "score": "3.51",
    "engagement": "7.00",
    "likes": 2,
    "recasts": 0,
    "replies": 0,
    "theme": "Apps/Games",
    "visibility": "general",
    "hash": "0x1340e73299127fc0742ef62b49061fe3fffda3eb",
    "cast_url": "https://farcaster.xyz/neynar/0x1340e732",
    "parent_hash": "0xe2b03ef3585dbcd1350a803b1b3e8a3bed4bbe92",
    "preview": "yes-this is very buildable in neynar studio, and it would look like a mini app where users pick squads before matches, earn points from real world cup results, and see live lead...",
    "text": "yes-this is very buildable in neynar studio, and it would look like a mini app where users pick squads before matches, earn points from real world cup results, and see live lead..."
  },
  {
    "rank": 107,
    "timestamp_utc": "2026-05-31 14:21:24",
    "type": "comment",
    "author": "@basedbid",
    "author_url": "https://farcaster.xyz/basedbid",
    "score": "2.59",
    "engagement": "6.90",
    "likes": 1,
    "recasts": 0,
    "replies": 1,
    "theme": "Base Culture",
    "visibility": "question",
    "hash": "0x8b27ebd5849bf63791e659f88a214e0990898da5",
    "cast_url": "https://farcaster.xyz/basedbid/0x8b27ebd5",
    "parent_hash": "0x9d9fbb5f6bbf2a01c9877f48dfccfc385fc68f29",
    "preview": "What are your apps? Wrote this article on X explaining what we built, would love your feedback! https://x.com/basedbidx/status/2044800813873201510",
    "text": "What are your apps? Wrote this article on X explaining what we built, would love your feedback! https://x.com/basedbidx/status/2044800813873201510"
  },
  {
    "rank": 108,
    "timestamp_utc": "2026-06-01 11:44:29",
    "type": "comment",
    "author": "@g4mer14",
    "author_url": "https://farcaster.xyz/g4mer14",
    "score": "1.00",
    "engagement": "6.90",
    "likes": 0,
    "recasts": 0,
    "replies": 1,
    "theme": "Security/Ops",
    "visibility": "general",
    "hash": "0x64a74485a62fd1f29b2c65680f4f5a808caa0c75",
    "cast_url": "https://farcaster.xyz/g4mer14/0x64a74485",
    "parent_hash": "0xcd76d75862eae98bc5e0b035151e1b7e4114d624",
    "preview": "This is a fantastic step towards user control and privacy on Farcaster! Having an independent private wallet is a game-changer for security, especially with EVM and Solana suppo...",
    "text": "This is a fantastic step towards user control and privacy on Farcaster! Having an independent private wallet is a game-changer for security, especially with EVM and Solana suppo..."
  },
  {
    "rank": 109,
    "timestamp_utc": "2026-06-01 06:24:49",
    "type": "comment",
    "author": "@sub",
    "author_url": "https://farcaster.xyz/sub",
    "score": "5.45",
    "engagement": "6.80",
    "likes": 6,
    "recasts": 0,
    "replies": 0,
    "theme": "Apps/Games",
    "visibility": "general",
    "hash": "0x48a5d9fba3c6b5c559606776c4855422da83b839",
    "cast_url": "https://farcaster.xyz/sub/0x48a5d9fb",
    "parent_hash": "",
    "preview": "Green only day 🙏 Framedl 2026-06-01 3/6*",
    "text": "Green only day 🙏 Framedl 2026-06-01 3/6*"
  },
  {
    "rank": 110,
    "timestamp_utc": "2026-06-01 07:28:58",
    "type": "comment",
    "author": "@cryptoexploit",
    "author_url": "https://farcaster.xyz/cryptoexploit",
    "score": "2.59",
    "engagement": "6.70",
    "likes": 1,
    "recasts": 0,
    "replies": 1,
    "theme": "Base Culture",
    "visibility": "general",
    "hash": "0xb7703da0fed52ba0e08b6ae040c1c6ffea69037e",
    "cast_url": "https://farcaster.xyz/cryptoexploit/0xb7703da0",
    "parent_hash": "0x5701264771faa3c601c8def24a9963bff18528dd",
    "preview": "That's right, we are building a project on the Base chain. We have big plans — this is not just another web app. Everything in due course, very soon. Follow our X",
    "text": "That's right, we are building a project on the Base chain. We have big plans — this is not just another web app. Everything in due course, very soon. Follow our X"
  },
  {
    "rank": 113,
    "timestamp_utc": "2026-05-31 15:16:26",
    "type": "comment",
    "author": "@lingaa",
    "author_url": "https://farcaster.xyz/lingaa",
    "score": "1.00",
    "engagement": "6.70",
    "likes": 0,
    "recasts": 0,
    "replies": 1,
    "theme": "Base Culture",
    "visibility": "question",
    "hash": "0xc5bbff358b2041e6115bc8c4cd25ba8c4b7d8c80",
    "cast_url": "https://farcaster.xyz/lingaa/0xc5bbff35",
    "parent_hash": "",
    "preview": "Maintain your Onchain Score above 85% and maintain your wallet balance On If you want to know your Onchain Score check here: https://base-analytics-app.vercel.app?ref=BFB9F030",
    "text": "Maintain your Onchain Score above 85% and maintain your wallet balance On If you want to know your Onchain Score check here: https://base-analytics-app.vercel.app?ref=BFB9F030"
  },
  {
    "rank": 114,
    "timestamp_utc": "2026-05-31 16:12:57",
    "type": "comment",
    "author": "@compassdotfun",
    "author_url": "https://farcaster.xyz/compassdotfun",
    "score": "1.00",
    "engagement": "6.60",
    "likes": 0,
    "recasts": 0,
    "replies": 2,
    "theme": "Base Culture",
    "visibility": "question",
    "hash": "0x8aff8cc0031d0d3926500718d802e07971833c16",
    "cast_url": "https://farcaster.xyz/compassdotfun/0x8aff8cc0",
    "parent_hash": "0x5d9da277e0fc798e3e66b5ff56c292305e5f0cb4",
    "preview": "Coined on https://zora.co/coin/base:0xe8949fff1ed3d478e32c8f77a7fde12dbdf32345?referrer=0x5d34f11158274277233b2c57a14bdf89d2bf828b",
    "text": "Coined on https://zora.co/coin/base:0xe8949fff1ed3d478e32c8f77a7fde12dbdf32345?referrer=0x5d34f11158274277233b2c57a14bdf89d2bf828b"
  },
  {
    "rank": 117,
    "timestamp_utc": "2026-05-31 15:53:18",
    "type": "comment",
    "author": "@frdysk",
    "author_url": "https://farcaster.xyz/frdysk",
    "score": "4.68",
    "engagement": "6.50",
    "likes": 4,
    "recasts": 1,
    "replies": 0,
    "theme": "Apps/Games",
    "visibility": "general",
    "hash": "0x108903137ab10e3c034ccdf1794650c7e8db848e",
    "cast_url": "https://farcaster.xyz/frdysk/0x10890313",
    "parent_hash": "",
    "preview": "unwanted growth inside you Framedl 2026-05-31 4/6*",
    "text": "unwanted growth inside you Framedl 2026-05-31 4/6*"
  },
  {
    "rank": 118,
    "timestamp_utc": "2026-06-01 04:42:05",
    "type": "comment",
    "author": "@and42",
    "author_url": "https://farcaster.xyz/and42",
    "score": "4.17",
    "engagement": "6.30",
    "likes": 3,
    "recasts": 0,
    "replies": 1,
    "theme": "Apps/Games",
    "visibility": "general",
    "hash": "0xfb20f7ceb1cf49569a1f40645fdeb430713224b7",
    "cast_url": "https://farcaster.xyz/and42/0xfb20f7ce",
    "parent_hash": "",
    "preview": "Right on time! Framedl PRO 2026-06-01 2/6*",
    "text": "Right on time! Framedl PRO 2026-06-01 2/6*"
  },
  {
    "rank": 120,
    "timestamp_utc": "2026-05-31 15:13:00",
    "type": "comment",
    "author": "@altagers",
    "author_url": "https://farcaster.xyz/altagers",
    "score": "3.51",
    "engagement": "6.10",
    "likes": 2,
    "recasts": 0,
    "replies": 1,
    "theme": "Base Culture",
    "visibility": "general",
    "hash": "0x2398c90662913e834d9f591647ac7aad8afa9769",
    "cast_url": "https://farcaster.xyz/altagers/0x2398c906",
    "parent_hash": "0x351d77f02a6ea8ea1cf5b3d608646c8876a2e272",
    "preview": "Haha, actually it’ll be more like \"builders code & base\"--> \"builders\"",
    "text": "Haha, actually it’ll be more like \"builders code & base\"--> \"builders\""
  },
  {
    "rank": 123,
    "timestamp_utc": "2026-06-01 10:19:44",
    "type": "comment",
    "author": "@yueqianling",
    "author_url": "https://farcaster.xyz/yueqianling",
    "score": "2.59",
    "engagement": "6.00",
    "likes": 1,
    "recasts": 0,
    "replies": 0,
    "theme": "Base Culture",
    "visibility": "general",
    "hash": "0xe1e1dfbf5d0ce21f060f2a75295f4c37e72d25c6",
    "cast_url": "https://farcaster.xyz/yueqianling/0xe1e1dfbf",
    "parent_hash": "",
    "preview": "Ajo/Esusu by Sujoodly is one of the most interesting financial experiments I’ve seen on ritual lately. Instead of creating a new system, this project brings the traditional rota...",
    "text": "Ajo/Esusu by Sujoodly is one of the most interesting financial experiments I’ve seen on ritual lately. Instead of creating a new system, this project brings the traditional rota..."
  },
  {
    "rank": 126,
    "timestamp_utc": "2026-06-01 09:27:21",
    "type": "comment",
    "author": "@3vortex",
    "author_url": "https://farcaster.xyz/3vortex",
    "score": "2.59",
    "engagement": "6.00",
    "likes": 1,
    "recasts": 0,
    "replies": 0,
    "theme": "Token/Promo",
    "visibility": "general",
    "hash": "0x8e72ea94c99db3f6726ca104dcf96bc2ebde0040",
    "cast_url": "https://farcaster.xyz/3vortex/0x8e72ea94",
    "parent_hash": "",
    "preview": "Beware of rug pulls and exit scams! Red flags include anonymous teams, sudden liquidity unlocks, and overly hyped promises. Always do your own research, check project transparen...",
    "text": "Beware of rug pulls and exit scams! Red flags include anonymous teams, sudden liquidity unlocks, and overly hyped promises. Always do your own research, check project transparen..."
  },
  {
    "rank": 127,
    "timestamp_utc": "2026-06-01 06:21:38",
    "type": "comment",
    "author": "@p1lot25",
    "author_url": "https://farcaster.xyz/p1lot25",
    "score": "2.59",
    "engagement": "6.00",
    "likes": 1,
    "recasts": 0,
    "replies": 0,
    "theme": "Token/Promo",
    "visibility": "general",
    "hash": "0x652fd8063ca6efea78a9e1182aeaaeeceff19960",
    "cast_url": "https://farcaster.xyz/p1lot25/0x652fd806",
    "parent_hash": "",
    "preview": "Navigating DeFi yield farming requires a sharp eye. Hunt for sustainable APYs by researching project fundamentals, team transparency, and tokenomics. Prioritize farms with real ...",
    "text": "Navigating DeFi yield farming requires a sharp eye. Hunt for sustainable APYs by researching project fundamentals, team transparency, and tokenomics. Prioritize farms with real ..."
  },
  {
    "rank": 128,
    "timestamp_utc": "2026-06-01 05:48:34",
    "type": "comment",
    "author": "@a1gorithm15",
    "author_url": "https://farcaster.xyz/a1gorithm15",
    "score": "2.59",
    "engagement": "6.00",
    "likes": 1,
    "recasts": 0,
    "replies": 0,
    "theme": "Protocol/Fork",
    "visibility": "general",
    "hash": "0x72f56fdbbf4520d1031b23d53cfe1ea60090fd40",
    "cast_url": "https://farcaster.xyz/a1gorithm15/0x72f56fdb",
    "parent_hash": "",
    "preview": "Enterprise blockchain like Hyperledger Fabric offers controlled access for businesses, focusing on privacy and efficiency. Public blockchains, however, are open to all, prioriti...",
    "text": "Enterprise blockchain like Hyperledger Fabric offers controlled access for businesses, focusing on privacy and efficiency. Public blockchains, however, are open to all, prioriti..."
  },
  {
    "rank": 129,
    "timestamp_utc": "2026-05-31 21:37:19",
    "type": "comment",
    "author": "@jbricha1",
    "author_url": "https://farcaster.xyz/jbricha1",
    "score": "2.59",
    "engagement": "6.00",
    "likes": 1,
    "recasts": 0,
    "replies": 0,
    "theme": "Base Culture",
    "visibility": "general",
    "hash": "0x74d2a313f57ae3026c608fd59e670fa0edba56fb",
    "cast_url": "https://farcaster.xyz/jbricha1/0x74d2a313",
    "parent_hash": "",
    "preview": "I’m on a little Zora 🟣 kick right now (I mean if posting every 2-4 days counts as a “kick” 😅) With that, here is my most recent Zora post, featuring a cool 😎 (to me, at least) c...",
    "text": "I’m on a little Zora 🟣 kick right now (I mean if posting every 2-4 days counts as a “kick” 😅) With that, here is my most recent Zora post, featuring a cool 😎 (to me, at least) c..."
  },
  {
    "rank": 133,
    "timestamp_utc": "2026-05-31 22:39:12",
    "type": "comment",
    "author": "@cameron",
    "author_url": "https://farcaster.xyz/cameron",
    "score": "3.51",
    "engagement": "5.90",
    "likes": 2,
    "recasts": 0,
    "replies": 1,
    "theme": "Base Culture",
    "visibility": "general",
    "hash": "0xe18249ecff0a9289bf51ad9f6669b9844731a7d9",
    "cast_url": "https://farcaster.xyz/cameron/0xe18249ec",
    "parent_hash": "0x513a1527e3a49836cddedfde70bb9b20b247e765",
    "preview": "I didn’t watch either. It just made me miss red vs blue",
    "text": "I didn’t watch either. It just made me miss red vs blue"
  },
  {
    "rank": 137,
    "timestamp_utc": "2026-05-31 13:47:52",
    "type": "comment",
    "author": "@bluewhale1",
    "author_url": "https://farcaster.xyz/bluewhale1",
    "score": "4.17",
    "engagement": "5.60",
    "likes": 3,
    "recasts": 0,
    "replies": 0,
    "theme": "Base Culture",
    "visibility": "general",
    "hash": "0x53da9329afe03ffae2821b42e2f620d4c2f7bf8e",
    "cast_url": "https://farcaster.xyz/bluewhale1/0x53da9329",
    "parent_hash": "",
    "preview": "I just opened a Warplet Blind Box! Collect unique Farcaster profile NFTs at Warplet Blind Box Miniapp on Base 🟦",
    "text": "I just opened a Warplet Blind Box! Collect unique Farcaster profile NFTs at Warplet Blind Box Miniapp on Base 🟦"
  },
  {
    "rank": 138,
    "timestamp_utc": "2026-05-31 15:05:05",
    "type": "comment",
    "author": "@weeonchain",
    "author_url": "https://farcaster.xyz/weeonchain",
    "score": "2.59",
    "engagement": "5.60",
    "likes": 1,
    "recasts": 0,
    "replies": 0,
    "theme": "Base Culture",
    "visibility": "general",
    "hash": "0x05a6ae3d66beb3fa84222c7001ed09334bbd5c22",
    "cast_url": "https://farcaster.xyz/weeonchain/0x05a6ae3d",
    "parent_hash": "",
    "preview": "Satisfying Sunday ! 😀 Hope you are spending some Quality~Time with Friends and Family. Soaking in the last day of the week, last day of the month. Fill your tank with these mome...",
    "text": "Satisfying Sunday ! 😀 Hope you are spending some Quality~Time with Friends and Family. Soaking in the last day of the week, last day of the month. Fill your tank with these mome..."
  },
  {
    "rank": 140,
    "timestamp_utc": "2026-06-01 06:49:51",
    "type": "comment",
    "author": "@nysons",
    "author_url": "https://farcaster.xyz/nysons",
    "score": "1.00",
    "engagement": "5.50",
    "likes": 0,
    "recasts": 0,
    "replies": 1,
    "theme": "Base Culture",
    "visibility": "general",
    "hash": "0x7d01660a555c26506e706e9fa6ed16f52c19ce34",
    "cast_url": "https://farcaster.xyz/nysons/0x7d01660a",
    "parent_hash": "0xa3bd18247f52e3a102bf807fee2b520218b069f7",
    "preview": "Excited to see what Base has in store for December 18th! Hoping it's a game-changer for the crypto gaming ecosystem. Big things coming!",
    "text": "Excited to see what Base has in store for December 18th! Hoping it's a game-changer for the crypto gaming ecosystem. Big things coming!"
  },
  {
    "rank": 143,
    "timestamp_utc": "2026-06-01 02:18:35",
    "type": "comment",
    "author": "@dcg201",
    "author_url": "https://farcaster.xyz/dcg201",
    "score": "3.51",
    "engagement": "5.40",
    "likes": 2,
    "recasts": 0,
    "replies": 0,
    "theme": "Security/Ops",
    "visibility": "general",
    "hash": "0x76c16a4772b7533de23e4de021875a3b12d27378",
    "cast_url": "https://farcaster.xyz/dcg201/0x76c16a47",
    "parent_hash": "",
    "preview": "Bia attended her first Hacker meet up at our meets at 11 years old. Now she is an adult hacking a future for the internet. Hear her speak at NY Tech Week: https://partiful.com/e...",
    "text": "Bia attended her first Hacker meet up at our meets at 11 years old. Now she is an adult hacking a future for the internet. Hear her speak at NY Tech Week: https://partiful.com/e..."
  },
  {
    "rank": 145,
    "timestamp_utc": "2026-05-31 17:07:48",
    "type": "comment",
    "author": "@sara2001",
    "author_url": "https://farcaster.xyz/sara2001",
    "score": "2.59",
    "engagement": "5.30",
    "likes": 1,
    "recasts": 0,
    "replies": 1,
    "theme": "Base Culture",
    "visibility": "question",
    "hash": "0xa7b8f91c629640c1664a62488ebbdd5ca143672c",
    "cast_url": "https://farcaster.xyz/sara2001/0xa7b8f91c",
    "parent_hash": "0x4f6d3aabe920a8a7d34251ddc91387b74f81a1e4",
    "preview": "dude do you think the blue mark hamon premium can raise my neynar score?",
    "text": "dude do you think the blue mark hamon premium can raise my neynar score?"
  },
  {
    "rank": 151,
    "timestamp_utc": "2026-06-01 03:09:42",
    "type": "comment",
    "author": "@rashedur",
    "author_url": "https://farcaster.xyz/rashedur",
    "score": "2.59",
    "engagement": "5.10",
    "likes": 1,
    "recasts": 0,
    "replies": 1,
    "theme": "Base Culture",
    "visibility": "general",
    "hash": "0xf7d4b2e06f6ecb5abff46d2b5eef19d0b550fa19",
    "cast_url": "https://farcaster.xyz/rashedur/0xf7d4b2e0",
    "parent_hash": "",
    "preview": "I just created my podium of today: 🥇Base - 🥈Beeper - 🥉Specuverse - /speculationcoin",
    "text": "I just created my podium of today: 🥇Base - 🥈Beeper - 🥉Specuverse - /speculationcoin"
  },
  {
    "rank": 152,
    "timestamp_utc": "2026-05-31 19:40:04",
    "type": "comment",
    "author": "@symbiotech",
    "author_url": "https://farcaster.xyz/symbiotech",
    "score": "3.51",
    "engagement": "5.10",
    "likes": 2,
    "recasts": 1,
    "replies": 0,
    "theme": "Base Culture",
    "visibility": "general",
    "hash": "0x601fb8532ca285a39bc8672e029a58ba1d61bbec",
    "cast_url": "https://farcaster.xyz/symbiotech/0x601fb853",
    "parent_hash": "",
    "preview": "Pending prop 🟡 https://nouns.build/dao/base/0x220e41499cf4d93a3629a5509410cbf9e6e0b109/vote/27",
    "text": "Pending prop 🟡 https://nouns.build/dao/base/0x220e41499cf4d93a3629a5509410cbf9e6e0b109/vote/27"
  },
  {
    "rank": 156,
    "timestamp_utc": "2026-05-31 17:00:00",
    "type": "comment",
    "author": "@lorenzo-007",
    "author_url": "https://farcaster.xyz/lorenzo-007",
    "score": "1.00",
    "engagement": "4.90",
    "likes": 0,
    "recasts": 0,
    "replies": 1,
    "theme": "Protocol/Fork",
    "visibility": "general",
    "hash": "0xca4b604b75d9e65d7cdef010281a328ab0be99ae",
    "cast_url": "https://farcaster.xyz/lorenzo-007/0xca4b604b",
    "parent_hash": "0x79ba86c8e582677ce8cc75e175a154df539c666f",
    "preview": "just saying if quorum keep moving like king von im not so sure if farcaster gonna survive these",
    "text": "just saying if quorum keep moving like king von im not so sure if farcaster gonna survive these"
  },
  {
    "rank": 160,
    "timestamp_utc": "2026-06-01 02:22:15",
    "type": "comment",
    "author": "@depressivehacks",
    "author_url": "https://farcaster.xyz/depressivehacks",
    "score": "2.59",
    "engagement": "4.70",
    "likes": 1,
    "recasts": 0,
    "replies": 1,
    "theme": "Base Culture",
    "visibility": "general",
    "hash": "0x54de95ee884e32595bd2486e9bd844c84ec5300e",
    "cast_url": "https://farcaster.xyz/depressivehacks/0x54de95ee",
    "parent_hash": "0xfc2fb40672bc7d075623e2dd471e407eb92b2878",
    "preview": "You should see Bluesky and/or Reddit. Also good contenders.",
    "text": "You should see Bluesky and/or Reddit. Also good contenders."
  },
  {
    "rank": 162,
    "timestamp_utc": "2026-06-01 10:00:42",
    "type": "comment",
    "author": "@stadiumcampsessi.base.eth",
    "author_url": "https://farcaster.xyz/stadiumcampsessi.base.eth",
    "score": "2.59",
    "engagement": "4.60",
    "likes": 1,
    "recasts": 0,
    "replies": 0,
    "theme": "Base Culture",
    "visibility": "general",
    "hash": "0xa55e1e6318a27a3be10ac4b45cdd0324139254e8",
    "cast_url": "https://farcaster.xyz/stadiumcampsessi.base.eth/0xa55e1e63",
    "parent_hash": "0x2250cec2055c50c7d511f7e1daa095cf58683200",
    "preview": "That's awesome! Congrats on winning the Equle game. I haven't played it yet, but I'll definitely check it out and see if I can beat your score. Always up for a fun blockchain-ba...",
    "text": "That's awesome! Congrats on winning the Equle game. I haven't played it yet, but I'll definitely check it out and see if I can beat your score. Always up for a fun blockchain-ba..."
  },
  {
    "rank": 164,
    "timestamp_utc": "2026-06-01 03:40:54",
    "type": "comment",
    "author": "@kaifovo",
    "author_url": "https://farcaster.xyz/kaifovo",
    "score": "2.59",
    "engagement": "4.50",
    "likes": 1,
    "recasts": 0,
    "replies": 1,
    "theme": "Protocol/Fork",
    "visibility": "general",
    "hash": "0xacf10eb5a39552650262397e25e9624700fc5b18",
    "cast_url": "https://farcaster.xyz/kaifovo/0xacf10eb5",
    "parent_hash": "0xcc681d240003a61354d4ba8404c574248a974009",
    "preview": "some quorum suggestions from fc community",
    "text": "some quorum suggestions from fc community"
  },
  {
    "rank": 166,
    "timestamp_utc": "2026-05-31 12:22:37",
    "type": "comment",
    "author": "@konohime",
    "author_url": "https://farcaster.xyz/konohime",
    "score": "1.00",
    "engagement": "4.50",
    "likes": 0,
    "recasts": 0,
    "replies": 1,
    "theme": "Protocol/Fork",
    "visibility": "question",
    "hash": "0xe7aae2192161571c5ddadefc0656dd875b4c1284",
    "cast_url": "https://farcaster.xyz/konohime/0xe7aae219",
    "parent_hash": "0x51738a45bf249414975fcf4e0018cc92f69bc9f3",
    "preview": "Thank you, glad to be back to Quorum 🥰 Any possibility to add the apk to the Aurora store for non-Play Store user?",
    "text": "Thank you, glad to be back to Quorum 🥰 Any possibility to add the apk to the Aurora store for non-Play Store user?"
  },
  {
    "rank": 167,
    "timestamp_utc": "2026-06-01 04:39:29",
    "type": "comment",
    "author": "@arjantupan",
    "author_url": "https://farcaster.xyz/arjantupan",
    "score": "4.68",
    "engagement": "4.40",
    "likes": 4,
    "recasts": 0,
    "replies": 0,
    "theme": "Apps/Games",
    "visibility": "general",
    "hash": "0x0a3242d3c6e0dc4d600c28fa4469360f2f28637f",
    "cast_url": "https://farcaster.xyz/arjantupan/0x0a3242d3",
    "parent_hash": "",
    "preview": "Framedl 2026-06-01 X/6* Oh no.",
    "text": "Framedl 2026-06-01 X/6* Oh no."
  },
  {
    "rank": 168,
    "timestamp_utc": "2026-06-01 05:00:12",
    "type": "comment",
    "author": "@vocsel",
    "author_url": "https://farcaster.xyz/vocsel",
    "score": "4.17",
    "engagement": "4.40",
    "likes": 3,
    "recasts": 0,
    "replies": 0,
    "theme": "Base Culture",
    "visibility": "question",
    "hash": "0x0817698067c3c2d4d6cd6a138e33239298d8334a",
    "cast_url": "https://farcaster.xyz/vocsel/0x08176980",
    "parent_hash": "",
    "preview": "https://zora.co/coin/base:0xe34be729fee8c8cb06595f7b5ed5218b80e5dd67?referrer=0xa5689ae6d06e832537250cceae70d2d1b7ed7b3f",
    "text": "https://zora.co/coin/base:0xe34be729fee8c8cb06595f7b5ed5218b80e5dd67?referrer=0xa5689ae6d06e832537250cceae70d2d1b7ed7b3f"
  },
  {
    "rank": 169,
    "timestamp_utc": "2026-06-01 02:23:11",
    "type": "comment",
    "author": "@geisha",
    "author_url": "https://farcaster.xyz/geisha",
    "score": "4.17",
    "engagement": "4.40",
    "likes": 3,
    "recasts": 0,
    "replies": 0,
    "theme": "Apps/Games",
    "visibility": "general",
    "hash": "0x5fb2573ff6b82d795e52caded04f4399d6171aaf",
    "cast_url": "https://farcaster.xyz/geisha/0x5fb2573f",
    "parent_hash": "",
    "preview": "Framedl 2026-06-01 X/6 Argh…. Thats NOT how you spell that word 🥲",
    "text": "Framedl 2026-06-01 X/6 Argh…. Thats NOT how you spell that word 🥲"
  },
  {
    "rank": 171,
    "timestamp_utc": "2026-06-01 07:22:49",
    "type": "comment",
    "author": "@officiallybmon1",
    "author_url": "https://farcaster.xyz/officiallybmon1",
    "score": "2.59",
    "engagement": "4.30",
    "likes": 1,
    "recasts": 0,
    "replies": 1,
    "theme": "Base Culture",
    "visibility": "general",
    "hash": "0x18459e0a05c7ab8af177cc327aad301258587b1f",
    "cast_url": "https://farcaster.xyz/officiallybmon1/0x18459e0a",
    "parent_hash": "0x977c51e8f51872917bf051793e5d592c51692723",
    "preview": "Happy new month Ari. Yes, base is for everyone.",
    "text": "Happy new month Ari. Yes, base is for everyone."
  },
  {
    "rank": 172,
    "timestamp_utc": "2026-05-31 15:25:37",
    "type": "comment",
    "author": "@altagers",
    "author_url": "https://farcaster.xyz/altagers",
    "score": "2.59",
    "engagement": "4.30",
    "likes": 1,
    "recasts": 0,
    "replies": 1,
    "theme": "Base Culture",
    "visibility": "general",
    "hash": "0xca4a41e31b8c3954321c7d4414e243a2b538c532",
    "cast_url": "https://farcaster.xyz/altagers/0xca4a41e3",
    "parent_hash": "0x3dd7366536e2782bfd4feda07f3022e651683b2c",
    "preview": "i think the best tag for this is #baseposting",
    "text": "i think the best tag for this is #baseposting"
  },
  {
    "rank": 176,
    "timestamp_utc": "2026-06-01 07:54:29",
    "type": "comment",
    "author": "@gamechanger5",
    "author_url": "https://farcaster.xyz/gamechanger5",
    "score": "3.51",
    "engagement": "4.20",
    "likes": 2,
    "recasts": 0,
    "replies": 0,
    "theme": "Base Culture",
    "visibility": "general",
    "hash": "0xb51d6283123fc7601ca577d3c135dd2b57f47aec",
    "cast_url": "https://farcaster.xyz/gamechanger5/0xb51d6283",
    "parent_hash": "0xae6e594f3034455f877d5ce80da01b4483ead1d3",
    "preview": "​ചലനങ്ങളിൽ നിന്നും, ചുറ്റുപാടുകളിൽ നിന്നും, മനുഷ്യർ ഈ ലോകത്തോട് എങ്ങനെ ഇടപഴകുന്നു എന്ന് കണ്ടുമൊക്കെയാണ് അവ കാര്യങ്ങൾ ഗ്രഹിക്കുന്നത്. ​ഇതിൽ ഏറ്റവും രസകരമായ കാര്യം, ZenO network ല...",
    "text": "​ചലനങ്ങളിൽ നിന്നും, ചുറ്റുപാടുകളിൽ നിന്നും, മനുഷ്യർ ഈ ലോകത്തോട് എങ്ങനെ ഇടപഴകുന്നു എന്ന് കണ്ടുമൊക്കെയാണ് അവ കാര്യങ്ങൾ ഗ്രഹിക്കുന്നത്. ​ഇതിൽ ഏറ്റവും രസകരമായ കാര്യം, ZenO network ല..."
  },
  {
    "rank": 177,
    "timestamp_utc": "2026-06-01 10:40:54",
    "type": "comment",
    "author": "@meshkitrader",
    "author_url": "https://farcaster.xyz/meshkitrader",
    "score": "2.59",
    "engagement": "4.10",
    "likes": 1,
    "recasts": 0,
    "replies": 1,
    "theme": "Apps/Games",
    "visibility": "general",
    "hash": "0x055c6c81ca53d8c570cee0b847440c5b8d968216",
    "cast_url": "https://farcaster.xyz/meshkitrader/0x055c6c81",
    "parent_hash": "",
    "preview": "2nd -ER in a row! I missed you too PRO Framedl PRO 2026-06-01 X/6*",
    "text": "2nd -ER in a row! I missed you too PRO Framedl PRO 2026-06-01 X/6*"
  },
  {
    "rank": 179,
    "timestamp_utc": "2026-06-01 09:34:29",
    "type": "comment",
    "author": "@trupty",
    "author_url": "https://farcaster.xyz/trupty",
    "score": "2.59",
    "engagement": "4.10",
    "likes": 1,
    "recasts": 0,
    "replies": 1,
    "theme": "Security/Ops",
    "visibility": "general",
    "hash": "0xe49c8e8c59418aa92d5dd6424c940af7255bb218",
    "cast_url": "https://farcaster.xyz/trupty/0xe49c8e8c",
    "parent_hash": "0xffd7a5ce4c0c157af4a43b4978ca5eae2731138a",
    "preview": "did hack your account",
    "text": "did hack your account"
  },
  {
    "rank": 180,
    "timestamp_utc": "2026-05-31 15:13:25",
    "type": "comment",
    "author": "@ryanhube",
    "author_url": "https://farcaster.xyz/ryanhube",
    "score": "2.59",
    "engagement": "4.10",
    "likes": 1,
    "recasts": 0,
    "replies": 1,
    "theme": "Base Culture",
    "visibility": "general",
    "hash": "0xaf865849d728aa68e1dab1a47129cb9773e928e8",
    "cast_url": "https://farcaster.xyz/ryanhube/0xaf865849",
    "parent_hash": "0xbe72e5dca5a118bc399be1f61186ed6f31c34a76",
    "preview": "You know I love blue",
    "text": "You know I love blue"
  },
  {
    "rank": 181,
    "timestamp_utc": "2026-05-31 14:21:15",
    "type": "comment",
    "author": "@itjeff",
    "author_url": "https://farcaster.xyz/itjeff",
    "score": "2.59",
    "engagement": "4.10",
    "likes": 1,
    "recasts": 0,
    "replies": 1,
    "theme": "Protocol/Fork",
    "visibility": "general",
    "hash": "0x9adeb0c0e9e5a65df5dd8be2a36cebc27b30b0da",
    "cast_url": "https://farcaster.xyz/itjeff/0x9adeb0c0",
    "parent_hash": "0xbac390e37cc79ba352a3ab03a6aadc2b68d2c82d",
    "preview": "Do a spaces live rip on Quorum",
    "text": "Do a spaces live rip on Quorum"
  },
  {
    "rank": 184,
    "timestamp_utc": "2026-05-31 22:33:38",
    "type": "comment",
    "author": "@donniecast",
    "author_url": "https://farcaster.xyz/donniecast",
    "score": "1.00",
    "engagement": "4.10",
    "likes": 0,
    "recasts": 0,
    "replies": 1,
    "theme": "Base Culture",
    "visibility": "general",
    "hash": "0x0059ff01fdcc9b25aabc36fa04458b6072be0e9a",
    "cast_url": "https://farcaster.xyz/donniecast/0x0059ff01",
    "parent_hash": "0x577b139ec8d7d31ef3ba4a73c0908a701bb76f1d",
    "preview": "now what are the odds they got that contract based a time and materials bid",
    "text": "now what are the odds they got that contract based a time and materials bid"
  },
  {
    "rank": 186,
    "timestamp_utc": "2026-05-31 19:14:15",
    "type": "comment",
    "author": "@izmaillevic",
    "author_url": "https://farcaster.xyz/izmaillevic",
    "score": "1.00",
    "engagement": "4.10",
    "likes": 0,
    "recasts": 0,
    "replies": 1,
    "theme": "Base Culture",
    "visibility": "general",
    "hash": "0x041662c78048d8da9b4ee8ecbeba4bfe45315dfa",
    "cast_url": "https://farcaster.xyz/izmaillevic/0x041662c7",
    "parent_hash": "",
    "preview": "I just created my @brnd podium of today: 🥇Base - 🥈Beeper - 🥉Betrmint -",
    "text": "I just created my @brnd podium of today: 🥇Base - 🥈Beeper - 🥉Betrmint -"
  },
  {
    "rank": 187,
    "timestamp_utc": "2026-06-01 07:00:59",
    "type": "comment",
    "author": "@randomy",
    "author_url": "https://farcaster.xyz/randomy",
    "score": "2.59",
    "engagement": "4.00",
    "likes": 1,
    "recasts": 0,
    "replies": 0,
    "theme": "Base Culture",
    "visibility": "general",
    "hash": "0x9a7891f77e8d7d7ddbddc4191dcae2b5fd17166d",
    "cast_url": "https://farcaster.xyz/randomy/0x9a7891f7",
    "parent_hash": "0x37cf7150721233beab5844d122883dc45c30e566",
    "preview": "One of the better dapps live on Base right now: Lucky38. On-chain games with verifiable results and instant USDC payouts. randomy.fun",
    "text": "One of the better dapps live on Base right now: Lucky38. On-chain games with verifiable results and instant USDC payouts. randomy.fun"
  },
  {
    "rank": 188,
    "timestamp_utc": "2026-05-31 21:11:54",
    "type": "comment",
    "author": "@trish",
    "author_url": "https://farcaster.xyz/trish",
    "score": "2.59",
    "engagement": "3.90",
    "likes": 1,
    "recasts": 0,
    "replies": 1,
    "theme": "Base Culture",
    "visibility": "question",
    "hash": "0xbe6defc105656ced7144669b36389a9a582cefb0",
    "cast_url": "https://farcaster.xyz/trish/0xbe6defc1",
    "parent_hash": "0xd3c4d0ee4e037bbf0286e6e967020d12a977da4f",
    "preview": "Did she just ask out of the blue?",
    "text": "Did she just ask out of the blue?"
  },
  {
    "rank": 189,
    "timestamp_utc": "2026-06-01 06:17:13",
    "type": "comment",
    "author": "@4050",
    "author_url": "https://farcaster.xyz/4050",
    "score": "1.00",
    "engagement": "3.90",
    "likes": 0,
    "recasts": 0,
    "replies": 1,
    "theme": "Base Culture",
    "visibility": "general",
    "hash": "0x5fc9b7caaa668a89252b9e6c156597d937a3ae64",
    "cast_url": "https://farcaster.xyz/4050/0x5fc9b7ca",
    "parent_hash": "0x66a39dbfd872075af0a36b7e29591bae97894778",
    "preview": "The beautiful and charming view of the blue sky is really beautiful. I enjoyed it.",
    "text": "The beautiful and charming view of the blue sky is really beautiful. I enjoyed it."
  },
  {
    "rank": 197,
    "timestamp_utc": "2026-05-31 16:20:47",
    "type": "comment",
    "author": "@cryp2",
    "author_url": "https://farcaster.xyz/cryp2",
    "score": "3.51",
    "engagement": "3.80",
    "likes": 2,
    "recasts": 0,
    "replies": 0,
    "theme": "Base Culture",
    "visibility": "general",
    "hash": "0x52010be3f193c818f7fb4af4b43587610deda1c4",
    "cast_url": "https://farcaster.xyz/cryp2/0x52010be3",
    "parent_hash": "",
    "preview": "Got my Warplet Blind Box! 🎉 Collect unique Farcaster Warplet profile NFTs on Base. 🟦",
    "text": "Got my Warplet Blind Box! 🎉 Collect unique Farcaster Warplet profile NFTs on Base. 🟦"
  },
  {
    "rank": 200,
    "timestamp_utc": "2026-05-31 19:13:49",
    "type": "comment",
    "author": "@maillev89",
    "author_url": "https://farcaster.xyz/maillev89",
    "score": "1.00",
    "engagement": "3.70",
    "likes": 0,
    "recasts": 0,
    "replies": 1,
    "theme": "Base Culture",
    "visibility": "general",
    "hash": "0x6ddf99a99147216408a764494b121a253c8f8661",
    "cast_url": "https://farcaster.xyz/maillev89/0x6ddf99a9",
    "parent_hash": "",
    "preview": "I just created my podium of today: 🥇Beeper - 🥈Base - 🥉QR -",
    "text": "I just created my podium of today: 🥇Beeper - 🥈Base - 🥉QR -"
  }
]
