[
  {
    "metric": "site_url",
    "value": "https://ael-dev3.github.io/Clawberto-Farcaster-Context/"
  },
  {
    "metric": "repo_url",
    "value": "https://github.com/ael-dev3/Clawberto-Farcaster-Context"
  },
  {
    "metric": "generated_at_utc",
    "value": "2026-05-25 10:51:36"
  },
  {
    "metric": "source",
    "value": "hypersnap"
  },
  {
    "metric": "hub_url",
    "value": "http://54.157.62.17:3381"
  },
  {
    "metric": "snapchain_shards",
    "value": "1,2"
  },
  {
    "metric": "collect_last_hours",
    "value": "24"
  },
  {
    "metric": "window_start_utc",
    "value": "2026-05-24 10:50:38"
  },
  {
    "metric": "window_end_utc",
    "value": "2026-05-25 10:50:35"
  },
  {
    "metric": "total_records",
    "value": 19011
  },
  {
    "metric": "posts",
    "value": 6183
  },
  {
    "metric": "comments",
    "value": 12828
  },
  {
    "metric": "selected_records",
    "value": 200
  },
  {
    "metric": "unique_authors",
    "value": 4877
  },
  {
    "metric": "total_likes",
    "value": 16663
  },
  {
    "metric": "total_recasts",
    "value": 2029
  },
  {
    "metric": "total_replies",
    "value": 7395
  },
  {
    "metric": "top_cast_score",
    "value": "8.71"
  },
  {
    "metric": "top_cast_author",
    "value": "@best"
  },
  {
    "metric": "top_cast_url",
    "value": "https://farcaster.xyz/best/0x313ff454"
  }
]
