[
  {
    "theme": "Base Culture",
    "casts": 124,
    "posts": 67,
    "comments": 57,
    "likes": 266,
    "avg_score": "2.54",
    "top_author": "@heavygweit",
    "top_cast_url": "https://farcaster.xyz/heavygweit/0x1223f899"
  },
  {
    "theme": "Apps/Games",
    "casts": 37,
    "posts": 12,
    "comments": 25,
    "likes": 149,
    "avg_score": "3.61",
    "top_author": "@azflin",
    "top_cast_url": "https://farcaster.xyz/azflin/0xccb14f80"
  },
  {
    "theme": "Security/Ops",
    "casts": 21,
    "posts": 8,
    "comments": 13,
    "likes": 37,
    "avg_score": "2.86",
    "top_author": "@kazani",
    "top_cast_url": "https://farcaster.xyz/kazani/0x20f76a9a"
  },
  {
    "theme": "Protocol/Fork",
    "casts": 12,
    "posts": 3,
    "comments": 9,
    "likes": 87,
    "avg_score": "3.61",
    "top_author": "@statuette",
    "top_cast_url": "https://farcaster.xyz/statuette/0x8158a676"
  },
  {
    "theme": "Token/Promo",
    "casts": 6,
    "posts": 5,
    "comments": 1,
    "likes": 4,
    "avg_score": "2.06",
    "top_author": "@yusufmarafaby",
    "top_cast_url": "https://farcaster.xyz/yusufmarafaby/0x0d2524b0"
  }
]
